Workbook

Sheet README
A1: Golden Delta Bank - starter data (SIMULATION, sample numbers only)
A2: All people, banks, rates and tax rates are made up. Business date is 2026-10-13 (the day after the last sample end of day, 2026-10-12). Opening balances are dated 2026-09-30; sample activity runs 2026-10-01 to 2026-10-12.
A4: Sheet | B4: Table | C4: Rows | D4: Stage
A5: Config | B5: tblConfig | C5: =COUNTA(Config!A:A)-1 -> 13 | D5: 1
A6: Users | B6: tblUsers | C6: =COUNTA(Users!A:A)-1 -> 49 | D6: 1
A7: Branches | B7: tblBranches | C7: =COUNTA(Branches!A:A)-1 -> 15 | D7: 1
A8: Customers | B8: tblCustomers | C8: =COUNTA(Customers!A:A)-1 -> 320 | D8: 1
A9: Products | B9: tblProducts | C9: =COUNTA(Products!A:A)-1 -> 5 | D9: 1
A10: RateTiers | B10: tblRateTiers | C10: =COUNTA(RateTiers!A:A)-1 -> 48 | D10: 1
A11: Fees | B11: tblFees | C11: =COUNTA(Fees!A:A)-1 -> 7 | D11: 1
A12: OtherBanks | B12: tblOtherBanks | C12: =COUNTA(OtherBanks!A:A)-1 -> 4 | D12: 1
A13: Chart | B13: tblChart | C13: =COUNTA(Chart!A:A)-1 -> 50 | D13: 1
A14: Accounts | B14: tblAccounts | C14: =COUNTA(Accounts!A:A)-1 -> 447 | D14: 1
A15: Transactions | B15: tblTransactions | C15: =COUNTA(Transactions!A:A)-1 -> 1337 | D15: 1
A16: InterbankTransfers | B16: tblInterbankTransfers | C16: =COUNTA(InterbankTransfers!A:A)-1 -> 36 | D16: 1
A17: Approvals | B17: tblApprovals | C17: =COUNTA(Approvals!A:A)-1 -> 9 | D17: 1
A18: Journal | B18: tblJournal | C18: =COUNTA(Journal!A:A)-1 -> 703 | D18: 1
A19: JournalLines | B19: tblJournalLines | C19: =COUNTA(JournalLines!A:A)-1 -> 2389 | D19: 1
A20: DailyClose | B20: tblDailyClose | C20: =COUNTA(DailyClose!A:A)-1 -> 12 | D20: 1
A21: Audit | B21: tblAudit | C21: =COUNTA(Audit!A:A)-1 -> 0 | D21: 1
A22: Log | B22: tblLog | C22: =COUNTA(Log!A:A)-1 -> 0 | D22: 1
A23: Currencies | B23: tblCurrencies | C23: =COUNTA(Currencies!A:A)-1 -> 5 | D23: 6 (reference)
A24: ExchangeRates | B24: tblExchangeRates | C24: =COUNTA(ExchangeRates!A:A)-1 -> 120 | D24: 6 (reference)
A25: TaxRates | B25: tblTaxRates | C25: =COUNTA(TaxRates!A:A)-1 -> 4 | D25: 2 (reference)
A26: BranchCosts | B26: tblBranchCosts | C26: =COUNTA(BranchCosts!A:A)-1 -> 150 | D26: 2 (reference)
A27: FixedAssets | B27: tblFixedAssets | C27: =COUNTA(FixedAssets!A:A)-1 -> 89 | D27: 2 (reference)
A29: Trial balance at 2026-10-13 (before the first end of day) | B29: Debit - Credit
A30: 1000 Cash in vault | B30: 4714385127
A31: 1100 Treasury and settlement balances | B31: 18772303480
A32: 2000 Savings deposits | B32: -1476938571
A33: 2010 Current account deposits | B33: -1315667248
A34: 2020 Fixed deposits | B34: -693575910
A35: 2900 Interbank payable (simulated) | B35: -427367
A36: 3000 Share capital | B36: -20000000000
A37: 4100 Fee income | B37: -79511
A38: Sum of all GL balances (must be 0) | B38: =SUM(B30:B37) -> 0
A40: What the first end of day (13 Oct) should do
A41: Fixed deposits maturing on 13 Oct: 2 | B41: 0060000398: principal 14,192,339, gross interest 214,635, tax 21,464, net 193,171; 0130000399: principal 9,473,371, gross interest 143,269, tax 14,327, net 128,942
A42: Accounts that become Dormant: 2 | B42: 0120000122, 0020000330
A43: Interbank transfers due to settle: 1 | B43: IB000035 (each settles or fails; sample failure rates apply)
A44: Interest accrued for 13 Oct (about) | B44: 325,059.83 MMK in total across accounts (before rounding per account)
A45: Pending approvals | B45: 4 requests wait for approval; 1 was rejected. See the Approvals sheet
A46: Reversed sample | B46: One deposit on 5 Oct was reversed on 6 Oct. See Journal.Status and Transactions.Status
A48: Notes
A49: Tables that look empty (Audit, Log) hold one blank row, because an Excel Table needs at least one. Treat a row with an empty key as no data.
A50: Stage 2, 6 reference sheets are not used by the Stage 1 code. They hold sample data for the later stages.
A51: Account balances here already include every posted sample transaction. Never edit Accounts.Balance, Transactions, Journal or JournalLines by hand.

Sheet Config
A1: Key | B1: Value
A2: BankName | B2: Golden Delta Bank (SIMULATION)
A3: BaseCurrency | B3: MMK
A4: BusinessDate | B4: 2026-10-13
A5: PolicyRate | B5: 0.10
A6: WithholdingTaxRate | B6: 0.10
A7: TellerLimit | B7: 5000000
A8: BranchManagerLimit | B8: 50000000
A9: DailyWithdrawalLimit | B9: 20000000
A10: DormantDays | B10: 365
A11: EarlyBreakRate | B11: 0.03
A12: DayCountBasis | B12: 365
... A14: ReserveRatio | B14: 0.05

Sheet Users
A1: UserID | B1: Name | C1: Role | D1: BranchID | E1: IsActive
A2: U001 | B2: System Admin | C2: Admin | D2: BR001 | E2: Yes
A3: U002 | B3: HO Officer 1 | C3: HeadOffice | D3: BR001 | E3: Yes
A4: U003 | B4: HO Officer 2 | C4: HeadOffice | D4: BR001 | E4: Yes
A5: U004 | B5: Internal Auditor | C5: Auditor | D5: BR001 | E5: Yes
A6: U005 | B6: Thura Su Lat | C6: Teller | D6: BR001 | E6: Yes
A7: U006 | B7: San Thu Soe | C7: Teller | D7: BR001 | E7: Yes
A8: U007 | B8: Zaw Min Soe | C8: BranchManager | D8: BR001 | E8: Yes
A9: U008 | B9: Htoo Thant Lwin | C9: Teller | D9: BR002 | E9: Yes
A10: U009 | B10: Htet Lin Swe | C10: Teller | D10: BR002 | E10: Yes
A11: U010 | B11: Mya Thu Naing | C11: BranchManager | D11: BR002 | E11: Yes
A12: U011 | B12: Ye Naing Maung | C12: Teller | D12: BR003 | E12: Yes
... A50: U049 | B50: Tun Thant Tun | C50: BranchManager | D50: BR015 | E50: Yes

Sheet Branches
A1: BranchID | B1: Name | C1: Type | D1: City | E1: Region | F1: PremisesType | G1: OpenDate | H1: Status | I1: VaultMin | J1: VaultMax
A2: BR001 | B2: Head Office | C2: HeadOffice | D2: Yangon | E2: Yangon Region | F2: Owned | G2: 39539 | H2: Open | I2: 500000000 | J2: 3000000000
A3: BR002 | B3: Hlaing Branch | C3: City | D3: Yangon | E3: Yangon Region | F3: Rented | G3: 40330 | H3: Open | I3: 100000000 | J3: 800000000
A4: BR003 | B4: Thingangyun Branch | C4: City | D4: Yangon | E4: Yangon Region | F4: Owned | G4: 40969 | H4: Open | I4: 100000000 | J4: 800000000
A5: BR004 | B5: Chanayethazan Branch | C5: City | D5: Mandalay | E5: Mandalay Region | F5: Owned | G5: 40756 | H5: Open | I5: 100000000 | J5: 800000000
A6: BR005 | B6: Aungmyaythazan Branch | C6: City | D6: Mandalay | E6: Mandalay Region | F6: Rented | G6: 41671 | H6: Open | I6: 100000000 | J6: 800000000
A7: BR006 | B7: Zabuthiri Branch | C7: City | D7: Naypyitaw | E7: Naypyitaw Union Territory | F7: Rented | G7: 41518 | H7: Open | I7: 100000000 | J7: 800000000
A8: BR007 | B8: Mawlamyine Branch | C8: City | D8: Mawlamyine | E8: Mon State | F8: Rented | G8: 42005 | H8: Open | I8: 100000000 | J8: 800000000
A9: BR008 | B9: Taunggyi Branch | C9: City | D9: Taunggyi | E9: Shan State | F9: Owned | G9: 42491 | H9: Open | I9: 100000000 | J9: 800000000
A10: BR009 | B10: Pyin Oo Lwin Branch | C10: Town | D10: Pyin Oo Lwin | E10: Mandalay Region | F10: Rented | G10: 42917 | H10: Open | I10: 40000000 | J10: 300000000
A11: BR010 | B11: Kyaukse Branch | C11: Town | D11: Kyaukse | E11: Mandalay Region | F11: Rented | G11: 43160 | H11: Open | I11: 40000000 | J11: 300000000
A12: BR011 | B12: Meiktila Branch | C12: Town | D12: Meiktila | E12: Mandalay Region | F12: Owned | G12: 43040 | H12: Open | I12: 40000000 | J12: 300000000
A13: BR012 | B13: Monywa Branch | C13: Town | D13: Monywa | E13: Sagaing Region | F13: Rented | G13: 43344 | H13: Open | I13: 40000000 | J13: 300000000
... A16: BR015 | B16: Nyaung-U Branch | C16: Town | D16: Nyaung-U | E16: Mandalay Region | F16: Rented | G16: 43831 | H16: Open | I16: 40000000 | J16: 300000000

Sheet Customers
A1: CustomerID | B1: Name | C1: CustomerType | D1: Phone | E1: Address | F1: HomeBranchID | G1: KYCLevel | H1: TaxExempt | I1: JoinDate | J1: Status
A2: C000001 | B2: Thet Htet Naing | C2: Individual | D2: 09363384229 | E2: No.158, 43th Street, Bago | F2: BR014 | G2: 1 | H2: No | I2: 43131 | J2: Active
A3: C000002 | B3: Eastern Garment Co., Ltd. | C3: Business | D3: 09423549521 | E3: No.213, 56th Street, Yangon | F3: BR002 | G3: 3 | H3: No | I3: 43157 | J3: Active
A4: C000003 | B4: Thet Lin Htay | C4: Individual | D4: 09352221721 | E4: No.68, 23th Street, Naypyitaw | F4: BR006 | G4: 1 | H4: No | I4: 43160 | J4: Active
A5: C000004 | B5: Lin Moe Soe | C5: Individual | D5: 09573011995 | E5: No.48, 35th Street, Yangon | F5: BR002 | G5: 1 | H5: No | I5: 43176 | J5: Active
A6: C000005 | B6: Shwe Moe Myint | C6: Individual | D6: 09695977814 | E6: No.84, 78th Street, Naypyitaw | F6: BR006 | G6: 1 | H6: No | I6: 43189 | J6: Active
A7: C000006 | B7: Eastern Logistics Co., Ltd. | C7: Business | D7: 09511046076 | E7: No.156, 87th Street, Mandalay | F7: BR004 | G7: 3 | H7: No | I7: 43235 | J7: Active
A8: C000007 | B8: Mya Thant Thein | C8: Individual | D8: 09287283525 | E8: No.63, 87th Street, Yangon | F8: BR001 | G8: 1 | H8: No | I8: 43258 | J8: Active
A9: C000008 | B9: Nilar Hlaing Win | C9: Individual | D9: 09280417312 | E9: No.22, 79th Street, Yangon | F9: BR001 | G9: 1 | H9: No | I9: 43265 | J9: Active
A10: C000009 | B10: Thandar Thu Swe | C10: Individual | D10: 09597112124 | E10: No.199, 78th Street, Mandalay | F10: BR005 | G10: 1 | H10: No | I10: 43284 | J10: Active
A11: C000010 | B11: Aung Khant Lwin | C11: Individual | D11: 09753693898 | E11: No.218, 49th Street, Yangon | F11: BR002 | G11: 3 | H11: No | I11: 43296 | J11: Active
A12: C000011 | B12: Min Pyae Swe | C12: Individual | D12: 09740170522 | E12: No.141, 44th Street, Mawlamyine | F12: BR007 | G12: 1 | H12: No | I12: 43308 | J12: Active
A13: C000012 | B13: Aye Mon Han | C13: Individual | D13: 09275869564 | E13: No.221, 80th Street, Yangon | F13: BR003 | G13: 1 | H13: No | I13: 43319 | J13: Active
... A321: C000320 | B321: Yadanar Thant Thein | C321: Individual | D321: 09293181323 | E321: No.127, 67th Street, Kyaukse | F321: BR010 | G321: 1 | H321: No | I321: 46264 | J321: Active

Sheet Products
A1: ProductCode | B1: Name | C1: Type | D1: Currency | E1: MinBalance | F1: MinOpening | G1: MaintenanceFeeCode | H1: IsActive
A2: SAV01 | B2: Regular Savings | C2: Savings | D2: MMK | E2: 10000 | F2: 10000 | H2: Yes
A3: SAV02 | B3: Premium Savings | C3: Savings | D3: MMK | E3: 5000000 | F3: 5000000 | H3: Yes
A4: CUR01 | B4: Current Account | C4: Current | D4: MMK | E4: 100000 | F4: 100000 | G4: MAINT_CUR_LOW | H4: Yes
A5: CUR02 | B5: Business Current | C5: Current | D5: MMK | E5: 1000000 | F5: 1000000 | G5: MAINT_CUR_LOW | H5: Yes
A6: FD01 | B6: Fixed Deposit | C6: Fixed | D6: MMK | E6: 0 | F6: 1000000 | H6: Yes

Sheet RateTiers
A1: RateID | B1: ProductCode | C1: TermMonths | D1: FromAmount | E1: ToAmount | F1: AnnualRate | G1: EffectiveFrom
A2: R0001 | B2: SAV01 | C2: 0 | D2: 0 | E2: 1000000 | F2: 0.02 | G2: 45292
A3: R0002 | B3: SAV01 | C3: 0 | D3: 1000000 | E3: 10000000 | F3: 0.025 | G3: 45292
A4: R0003 | B4: SAV01 | C4: 0 | D4: 10000000 | F4: 0.03 | G4: 45292
A5: R0004 | B5: SAV02 | C5: 0 | D5: 0 | E5: 50000000 | F5: 0.035 | G5: 45292
A6: R0005 | B6: SAV02 | C6: 0 | D6: 50000000 | F6: 0.04 | G6: 45292
A7: R0006 | B7: CUR01 | C7: 0 | D7: 0 | F7: 0 | G7: 45292
A8: R0007 | B8: CUR02 | C8: 0 | D8: 0 | E8: 10000000 | F8: 0 | G8: 45292
A9: R0008 | B9: CUR02 | C9: 0 | D9: 10000000 | F9: 0.003 | G9: 45292
A10: R0009 | B10: FD01 | C10: 3 | D10: 1000000 | E10: 50000000 | F10: 0.05 | G10: 45292
A11: R0010 | B11: FD01 | C11: 3 | D11: 50000000 | F11: 0.055 | G11: 45292
A12: R0011 | B12: FD01 | C12: 6 | D12: 1000000 | E12: 50000000 | F12: 0.06 | G12: 45292
A13: R0012 | B13: FD01 | C13: 6 | D13: 50000000 | F13: 0.065 | G13: 45292
A14: R0013 | B14: FD01 | C14: 12 | D14: 1000000 | E14: 50000000 | F14: 0.075 | G14: 45292
A15: R0014 | B15: FD01 | C15: 12 | D15: 50000000 | F15: 0.08 | G15: 45292
A16: R0015 | B16: FD01 | C16: 24 | D16: 1000000 | E16: 50000000 | F16: 0.08 | G16: 45292
A17: R0016 | B17: FD01 | C17: 24 | D17: 50000000 | F17: 0.085 | G17: 45292
A18: R0017 | B18: SAV01 | C18: 0 | D18: 0 | E18: 1000000 | F18: 0.025 | G18: 45658
A19: R0018 | B19: SAV01 | C19: 0 | D19: 1000000 | E19: 10000000 | F19: 0.03 | G19: 45658
A20: R0019 | B20: SAV01 | C20: 0 | D20: 10000000 | F20: 0.035 | G20: 45658
A21: R0020 | B21: SAV02 | C21: 0 | D21: 0 | E21: 50000000 | F21: 0.04 | G21: 45658
A22: R0021 | B22: SAV02 | C22: 0 | D22: 50000000 | F22: 0.045 | G22: 45658
A23: R0022 | B23: CUR01 | C23: 0 | D23: 0 | F23: 0 | G23: 45658
A24: R0023 | B24: CUR02 | C24: 0 | D24: 0 | E24: 10000000 | F24: 0 | G24: 45658
A25: R0024 | B25: CUR02 | C25: 0 | D25: 10000000 | F25: 0.004 | G25: 45658
A26: R0025 | B26: FD01 | C26: 3 | D26: 1000000 | E26: 50000000 | F26: 0.055 | G26: 45658
A27: R0026 | B27: FD01 | C27: 3 | D27: 50000000 | F27: 0.06 | G27: 45658
A28: R0027 | B28: FD01 | C28: 6 | D28: 1000000 | E28: 50000000 | F28: 0.065 | G28: 45658
A29: R0028 | B29: FD01 | C29: 6 | D29: 50000000 | F29: 0.07 | G29: 45658
A30: R0029 | B30: FD01 | C30: 12 | D30: 1000000 | E30: 50000000 | F30: 0.08 | G30: 45658
A31: R0030 | B31: FD01 | C31: 12 | D31: 50000000 | F31: 0.085 | G31: 45658
A32: R0031 | B32: FD01 | C32: 24 | D32: 1000000 | E32: 50000000 | F32: 0.085 | G32: 45658
A33: R0032 | B33: FD01 | C33: 24 | D33: 50000000 | F33: 0.09 | G33: 45658
A34: R0033 | B34: SAV01 | C34: 0 | D34: 0 | E34: 1000000 | F34: 0.03 | G34: 46023
A35: R0034 | B35: SAV01 | C35: 0 | D35: 1000000 | E35: 10000000 | F35: 0.035 | G35: 46023
A36: R0035 | B36: SAV01 | C36: 0 | D36: 10000000 | F36: 0.04 | G36: 46023
A37: R0036 | B37: SAV02 | C37: 0 | D37: 0 | E37: 50000000 | F37: 0.045 | G37: 46023
A38: R0037 | B38: SAV02 | C38: 0 | D38: 50000000 | F38: 0.05 | G38: 46023
A39: R0038 | B39: CUR01 | C39: 0 | D39: 0 | F39: 0 | G39: 46023
A40: R0039 | B40: CUR02 | C40: 0 | D40: 0 | E40: 10000000 | F40: 0 | G40: 46023
A41: R0040 | B41: CUR02 | C41: 0 | D41: 10000000 | F41: 0.005 | G41: 46023
A42: R0041 | B42: FD01 | C42: 3 | D42: 1000000 | E42: 50000000 | F42: 0.06 | G42: 46023
A43: R0042 | B43: FD01 | C43: 3 | D43: 50000000 | F43: 0.065 | G43: 46023
A44: R0043 | B44: FD01 | C44: 6 | D44: 1000000 | E44: 50000000 | F44: 0.07 | G44: 46023
A45: R0044 | B45: FD01 | C45: 6 | D45: 50000000 | F45: 0.075 | G45: 46023
A46: R0045 | B46: FD01 | C46: 12 | D46: 1000000 | E46: 50000000 | F46: 0.085 | G46: 46023
A47: R0046 | B47: FD01 | C47: 12 | D47: 50000000 | F47: 0.09 | G47: 46023
A48: R0047 | B48: FD01 | C48: 24 | D48: 1000000 | E48: 50000000 | F48: 0.09 | G48: 46023
A49: R0048 | B49: FD01 | C49: 24 | D49: 50000000 | F49: 0.095 | G49: 46023

Sheet Fees
A1: FeeCode | B1: Name | C1: Method | D1: FlatAmount | E1: Rate | F1: MinFee | G1: MaxFee | H1: Currency | I1: IncomeGL
A2: CROSS_BRANCH_WD | B2: Cash withdrawal at another branch | C2: Percent | D2: 0 | E2: 0.001 | F2: 500 | G2: 20000 | H2: MMK | I2: 4100
A3: TRANSFER_SAME | B3: Transfer within the same branch | C3: Flat | D3: 0 | E3: 0 | F3: 0 | G3: 0 | H3: MMK | I3: 4100
A4: TRANSFER_BRANCH | B4: Transfer to another branch | C4: Percent | D4: 0 | E4: 0.0005 | F4: 300 | G4: 10000 | H4: MMK | I4: 4100
A5: INTERBANK_OUT | B5: Transfer to another bank (simulated) | C5: Percent | D5: 0 | E5: 0.001 | F5: 1000 | G5: 25000 | H5: MMK | I5: 4100
A6: INTERBANK_IN | B6: Transfer from another bank (simulated) | C6: Flat | D6: 0 | E6: 0 | F6: 0 | G6: 0 | H6: MMK | I6: 4100
A7: MAINT_CUR_LOW | B7: Monthly fee, current account below minimum balance | C7: Flat | D7: 3000 | E7: 0 | F7: 0 | G7: 0 | H7: MMK | I7: 4100
A8: FD_EARLY_BREAK | B8: Early break of fixed deposit | C8: Percent | D8: 0 | E8: 0.005 | F8: 0 | G8: 0 | H8: MMK | I8: 4100

Sheet OtherBanks
A1: BankCode | B1: Name | C1: SettleDays | D1: FailRate | E1: ReturnRate
A2: OB01 | B2: Sunrise Commercial Bank (simulated) | C2: 1 | D2: 0.03 | E2: 0.01
A3: OB02 | B3: Golden River Bank (simulated) | C3: 2 | D3: 0.04 | E3: 0.01
A4: OB03 | B4: Delta Savings Bank (simulated) | C4: 2 | D4: 0.05 | E4: 0.02
A5: OB04 | B5: Capital Trust Bank (simulated) | C5: 1 | D5: 0.02 | E5: 0.01

Sheet Chart
A1: GLCode | B1: Name | C1: Type | D1: NormalSide | E1: Stage | F1: IsActive
A2: 1000 | B2: Cash in vault | C2: Asset | D2: Debit | E2: 1 | F2: Yes
A3: 1100 | B3: Treasury and settlement balances | C3: Asset | D3: Debit | E3: 1 | F3: Yes
A4: 1300 | B4: Loans receivable | C4: Asset | D4: Debit | E4: 3 | F4: No
A5: 1310 | B5: Interest receivable | C5: Asset | D5: Debit | E5: 3 | F5: No
A6: 1400 | B6: Repossessed assets held for sale | C6: Asset | D6: Debit | E6: 4 | F6: No
A7: 1500 | B7: Premises and equipment, cost | C7: Asset | D7: Debit | E7: 2 | F7: No
A8: 1510 | B8: Accumulated depreciation | C8: Asset | D8: Credit | E8: 2 | F8: No
A9: 1600 | B9: Business investments | C9: Asset | D9: Debit | E9: 7 | F9: No
A10: 1700 | B10: Foreign currency holdings | C10: Asset | D10: Debit | E10: 6 | F10: No
A11: 1800 | B11: Prepaid expenses | C11: Asset | D11: Debit | E11: 2 | F11: No
A12: 1900 | B12: Inter-branch clearing | C12: Asset | D12: Debit | E12: 1 | F12: Yes
A13: 2000 | B13: Savings deposits | C13: Liability | D13: Credit | E13: 1 | F13: Yes
... A51: 5500 | B51: Other expenses | C51: Expense | D51: Debit | E51: 2 | F51: No

Sheet Accounts
A1: AccountNo | B1: CustomerID | C1: BranchID | D1: ProductCode | E1: Currency | F1: Status | G1: OpenDate | H1: TermMonths | I1: MaturityDate | J1: LockedRate | K1: PayoutAccountNo | L1: Balance | M1: AccruedInterest | N1: LastAccrualDate | O1: LastActivityDate | P1: ClosedDate
A2: 0010000009 | B2: C000007 | C2: BR001 | D2: SAV01 | E2: MMK | F2: Active | G2: 43503 | L2: 3664780 | M2: 3649.3593 | N2: 46307 | O2: 46301
A3: 0010000010 | B3: C000007 | C3: BR001 | D3: CUR01 | E3: MMK | F3: Dormant | G3: 44223 | L3: 1167172 | M3: 0 | N3: 46307 | O3: 45870
A4: 0010000011 | B4: C000008 | C4: BR001 | D4: SAV01 | E4: MMK | F4: Active | G4: 45199 | L4: 3940665 | M4: 4534.464 | N4: 46307 | O4: 46250
A5: 0010000024 | B5: C000017 | C5: BR001 | D5: CUR02 | E5: MMK | F5: Active | G5: 45515 | L5: 25028259 | M5: 4114.2348 | N5: 46307 | O5: 46236
A6: 0010000025 | B6: C000017 | C6: BR001 | D6: SAV01 | E6: MMK | F6: Active | G6: 45955 | L6: 277992 | M6: 808.6846 | N6: 46307 | O6: 46304
A7: 0010000031 | B7: C000023 | C7: BR001 | D7: SAV02 | E7: MMK | F7: Active | G7: 43756 | L7: 5519618 | M7: 7922.6207 | N7: 46307 | O7: 46301
A8: 0010000036 | B8: C000028 | C8: BR001 | D8: SAV01 | E8: MMK | F8: Active | G8: 43982 | L8: 5890348 | M8: 6578.5535 | N8: 46307 | O8: 46307
A9: 0010000076 | B9: C000059 | C9: BR001 | D9: SAV01 | E9: MMK | F9: Active | G9: 46141 | L9: 4373333 | M9: 4832.6903 | N9: 46307 | O9: 46305
A10: 0010000092 | B10: C000072 | C10: BR001 | D10: CUR02 | E10: MMK | F10: Active | G10: 46281 | L10: 17801658 | M10: 2949.7281 | N10: 46307 | O10: 46301
A11: 0010000120 | B11: C000096 | C11: BR001 | D11: SAV01 | E11: MMK | F11: Active | G11: 45277 | L11: 2494569 | M11: 2749.124 | N11: 46307 | O11: 46306
A12: 0010000130 | B12: C000104 | C12: BR001 | D12: SAV01 | E12: MMK | F12: Active | G12: 45828 | L12: 775946 | M12: 815.4856 | N12: 46307 | O12: 46300
A13: 0010000131 | B13: C000104 | C13: BR001 | D13: CUR01 | E13: MMK | F13: Active | G13: 46056 | L13: 3927282 | M13: 0 | N13: 46307 | O13: 46296
... A25: 0010000367 | B25: C000293 | C25: BR001 | D25: CUR01 | E25: MMK | F25: Active | G25: 46284 | L25: 393034 | M25: 0 | N25: 46307 | O25: 46300
A26: 0010000405 | B26: C000248 | C26: BR001 | D26: FD01 | E26: MMK | F26: Active | G26: 46122 | H26: 12 | I26: 46487 | J26: 0.085 | K26: 0010000312 | L26: 14975162 | M26: 648650.17 | N26: 46307 | O26: 46122
A27: 0010000422 | B27: C000023 | C27: BR001 | D27: FD01 | E27: MMK | F27: Active | G27: 46012 | H27: 24 | I27: 46742 | J27: 0.085 | K27: 0010000031 | L27: 6675443 | M27: 460148.34 | N27: 46307 | O27: 46012
A28: 0010000445 | B28: C000007 | C28: BR001 | D28: SAV01 | E28: MMK | F28: Active | G28: 46302 | L28: 126516 | M28: 119.8508 | N28: 46307 | O28: 46306
A29: 0020000002 | B29: C000002 | C29: BR002 | D29: CUR02 | E29: MMK | F29: Active | G29: 43570 | L29: 47796356 | M29: 7900.0332 | N29: 46307 | O29: 46306
A30: 0020000005 | B30: C000004 | C30: BR002 | D30: SAV01 | E30: MMK | F30: Active | G30: 44354 | L30: 377638 | M30: 483.6583 | N30: 46307 | O30: 46306
A31: 0020000013 | B31: C000010 | C31: BR002 | D31: SAV01 | E31: MMK | F31: Active | G31: 45440 | L31: 2647378 | M31: 2041.0314 | N31: 46307 | O31: 46301
A32: 0020000030 | B32: C000022 | C32: BR002 | D32: SAV01 | E32: MMK | F32: Active | G32: 46053 | L32: 1010809 | M32: 744.0482 | N32: 46307 | O32: 46303
A33: 0020000034 | B33: C000026 | C33: BR002 | D33: SAV01 | E33: MMK | F33: Active | G33: 45754 | L33: 126908 | M33: 240.4752 | N33: 46307 | O33: 46304
A34: 0020000041 | B34: C000033 | C34: BR002 | D34: SAV01 | E34: MMK | F34: Active | G34: 44032 | L34: 8119875 | M34: 9097.7828 | N34: 46307 | O34: 46300
A35: 0020000069 | B35: C000054 | C35: BR002 | D35: SAV01 | E35: MMK | F35: Active | G35: 45615 | L35: 5571095 | M35: 5821.9031 | N35: 46307 | O35: 46307
A36: 0020000070 | B36: C000054 | C36: BR002 | D36: CUR01 | E36: MMK | F36: Active | G36: 45468 | L36: 776704 | M36: 0 | N36: 46307 | O36: 46272
A37: 0020000085 | B37: C000067 | C37: BR002 | D37: CUR02 | E37: MMK | F37: Active | G37: 44425 | L37: 41363081 | M37: 6761.1729 | N37: 46307 | O37: 46307
A38: 0020000086 | B38: C000067 | C38: BR002 | D38: SAV01 | E38: MMK | F38: Active | G38: 45676 | L38: 8231473 | M38: 5346.03 | N38: 46307 | O38: 46304
A39: 0020000096 | B39: C000075 | C39: BR002 | D39: SAV02 | E39: MMK | F39: Active | G39: 45989 | L39: 12065802 | M39: 18042.599 | N39: 46307 | O39: 46300
... A60: 0020000357 | B60: C000286 | C60: BR002 | D60: SAV01 | E60: MMK | F60: Active | G60: 46188 | L60: 2285718 | M60: 2630.1408 | N60: 46307 | O60: 46287
A61: 0020000423 | B61: C000263 | C61: BR002 | D61: FD01 | E61: MMK | F61: Active | G61: 46287 | H61: 3 | I61: 46378 | J61: 0.06 | K61: 0020000330 | L61: 5664075 | M61: 19552.697 | N61: 46307 | O61: 46287
A62: 0030000015 | B62: C000012 | C62: BR003 | D62: SAV01 | E62: MMK | F62: Active | G62: 44567 | L62: 11294647 | M62: 13707.504 | N62: 46307 | O62: 46307
A63: 0030000016 | B63: C000012 | C63: BR003 | D63: CUR01 | E63: MMK | F63: Active | G63: 44532 | L63: 5510281 | M63: 0 | N63: 46307 | O63: 46306
A64: 0030000033 | B64: C000025 | C64: BR003 | D64: SAV01 | E64: MMK | F64: Active | G64: 45868 | L64: 1116752 | M64: 1246.3775 | N64: 46307 | O64: 46299
A65: 0030000045 | B65: C000037 | C65: BR003 | D65: CUR02 | E65: MMK | F65: Active | G65: 46287 | L65: 61601285 | M65: 10110.556 | N65: 46307 | O65: 46305
A66: 0030000046 | B66: C000037 | C66: BR003 | D66: SAV01 | E66: MMK | F66: Active | G66: 44700 | L66: 33603338 | M66: 40561.694 | N66: 46307 | O66: 46306
A67: 0030000047 | B67: C000038 | C67: BR003 | D67: SAV01 | E67: MMK | F67: Active | G67: 44684 | L67: 912694 | M67: 1124.8236 | N67: 46307 | O67: 46304
A68: 0030000057 | B68: C000046 | C68: BR003 | D68: CUR02 | E68: MMK | F68: Active | G68: 46287 | L68: 122125089 | M68: 20075.357 | N68: 46307 | O68: 46287
A69: 0030000065 | B69: C000052 | C69: BR003 | D69: SAV01 | E69: MMK | F69: Active | G69: 45190 | L69: 1953721 | M69: 2166.4057 | N69: 46307 | O69: 46301
A70: 0030000066 | B70: C000052 | C70: BR003 | D70: CUR01 | E70: MMK | F70: Active | G70: 45004 | L70: 623935 | M70: 0 | N70: 46307 | O70: 46307
A71: 0030000072 | B71: C000056 | C71: BR003 | D71: CUR02 | E71: MMK | F71: Active | G71: 44581 | L71: 14217637 | M71: 584.2866 | N71: 46307 | O71: 46305
A72: 0030000073 | B72: C000056 | C72: BR003 | D72: SAV01 | E72: MMK | F72: Active | G72: 43995 | L72: 3797430 | M72: 4369.6452 | N72: 46307 | O72: 46255
A73: 0030000077 | B73: C000060 | C73: BR003 | D73: SAV01 | E73: MMK | F73: Dormant | G73: 43921 | L73: 787375 | M73: 776.5896 | N73: 46307 | O73: 45835
... A80: 0030000108 | B80: C000085 | C80: BR003 | D80: CUR01 | E80: MMK | F80: Active | G80: 44992 | L80: 661888 | M80: 0 | N80: 46307 | O80: 46307
A81: 0030000128 | B81: C000102 | C81: BR003 | D81: SAV01 | E81: MMK | F81: Closed | G81: 44964 | L81: 0 | M81: 0 | O81: 46135 | P81: 46135
A82: 0030000148 | B82: C000119 | C82: BR003 | D82: SAV01 | E82: MMK | F82: Active | G82: 45780 | L82: 1801399 | M82: 1914.634 | N82: 46307 | O82: 46300
A83: 0030000149 | B83: C000119 | C83: BR003 | D83: CUR01 | E83: MMK | F83: Active | G83: 45624 | L83: 4063211 | M83: 0 | N83: 46307 | O83: 46298
A84: 0030000170 | B84: C000135 | C84: BR003 | D84: SAV01 | E84: MMK | F84: Active | G84: 45129 | L84: 640701 | M84: 846.8285 | N84: 46307 | O84: 46304
A85: 0030000177 | B85: C000140 | C85: BR003 | D85: SAV02 | E85: MMK | F85: Active | G85: 45400 | L85: 13669635 | M85: 19877.992 | N85: 46307 | O85: 46303
A86: 0030000180 | B86: C000142 | C86: BR003 | D86: SAV01 | E86: MMK | F86: Active | G86: 45690 | L86: 2281774 | M86: 1870.3689 | N86: 46307 | O86: 46301
A87: 0030000181 | B87: C000142 | C87: BR003 | D87: CUR01 | E87: MMK | F87: Active | G87: 44734 | L87: 4638359 | M87: 0 | N87: 46307 | O87: 46303
A88: 0030000194 | B88: C000154 | C88: BR003 | D88: SAV01 | E88: MMK | F88: Active | G88: 44888 | L88: 13082936 | M88: 17203.58 | N88: 46307 | O88: 46306
A89: 0030000231 | B89: C000186 | C89: BR003 | D89: CUR02 | E89: MMK | F89: Active | G89: 45801 | L89: 17341826 | M89: 2733.7655 | N89: 46307 | O89: 46305
A90: 0030000232 | B90: C000186 | C90: BR003 | D90: SAV01 | E90: MMK | F90: Active | G90: 45040 | L90: 14464725 | M90: 15068.227 | N90: 46307 | O90: 46302
A91: 0030000245 | B91: C000196 | C91: BR003 | D91: SAV01 | E91: MMK | F91: Active | G91: 45386 | L91: 4978013 | M91: 5728.1244 | N91: 46307 | O91: 46296
A92: 0030000253 | B92: C000203 | C92: BR003 | D92: SAV01 | E92: MMK | F92: Active | G92: 46033 | L92: 118590 | M92: 130.3529 | N92: 46307 | O92: 46297
A93: 0030000254 | B93: C000203 | C93: BR003 | D93: CUR01 | E93: MMK | F93: Active | G93: 45893 | L93: 2566238 | M93: 0 | N93: 46307 | O93: 46303
... A103: 0030000396 | B103: C000319 | C103: BR003 | D103: SAV01 | E103: MMK | F103: Active | G103: 46267 | L103: 1172020 | M103: 1423.0178 | N103: 46307 | O103: 46303
A104: 0030000408 | B104: C000012 | C104: BR003 | D104: FD01 | E104: MMK | F104: Active | G104: 46269 | H104: 6 | I104: 46450 | J104: 0.07 | K104: 0030000015 | L104: 6193307 | M104: 46322.543 | N104: 46307 | O104: 46269
A105: 0030000419 | B105: C000300 | C105: BR003 | D105: FD01 | E105: MMK | F105: Active | G105: 46289 | H105: 12 | I105: 46654 | J105: 0.085 | K105: 0030000375 | L105: 2001793 | M105: 8857.2488 | N105: 46307 | O105: 46289
A106: 0030000426 | B106: C000277 | C106: BR003 | D106: FD01 | E106: MMK | F106: Active | G106: 46283 | H106: 12 | I106: 46648 | J106: 0.085 | K106: 0030000347 | L106: 11940572 | M106: 69517.029 | N106: 46307 | O106: 46283
A107: 0030000429 | B107: C000060 | C107: BR003 | D107: FD01 | E107: MMK | F107: Active | G107: 46286 | H107: 6 | I107: 46467 | J107: 0.07 | K107: 0030000077 | L107: 24661209 | M107: 104050.03 | N107: 46307 | O107: 46286
A108: 0030000438 | B108: C000314 | C108: BR003 | D108: FD01 | E108: MMK | F108: Active | G108: 46282 | H108: 6 | I108: 46463 | J108: 0.07 | K108: 0030000390 | L108: 8820584 | M108: 43982.09 | N108: 46307 | O108: 46282
A109: 0030000444 | B109: C000062 | C109: BR003 | D109: SAV01 | E109: MMK | F109: Active | G109: 46301 | L109: 1962770 | M109: 760.4476 | N109: 46307 | O109: 46306
A110: 0040000008 | B110: C000006 | C110: BR004 | D110: CUR02 | E110: MMK | F110: Active | G110: 45032 | L110: 3023404 | M110: 0 | N110: 46307 | O110: 46297
A111: 0040000017 | B111: C000013 | C111: BR004 | D111: SAV02 | E111: MMK | F111: Active | G111: 45416 | L111: 26160838 | M111: 38703.706 | N111: 46307 | O111: 46237
A112: 0040000018 | B112: C000013 | C112: BR004 | D112: CUR01 | E112: MMK | F112: Active | G112: 44696 | L112: 2501288 | M112: 0 | N112: 46307 | O112: 46298
A113: 0040000028 | B113: C000020 | C113: BR004 | D113: SAV01 | E113: MMK | F113: Active | G113: 44214 | L113: 1645450 | M113: 1725.3965 | N113: 46307 | O113: 46302
A114: 0040000062 | B114: C000050 | C114: BR004 | D114: SAV01 | E114: MMK | F114: Active | G114: 43800 | L114: 2812052 | M114: 2657.0413 | N114: 46307 | O114: 46307
A115: 0040000063 | B115: C000050 | C115: BR004 | D115: CUR01 | E115: MMK | F115: Active | G115: 45523 | L115: 2900571 | M115: 0 | N115: 46307 | O115: 46305
A116: 0040000071 | B116: C000055 | C116: BR004 | D116: CUR02 | E116: MMK | F116: Active | G116: 44503 | L116: 26501510 | M116: 4449.976 | N116: 46307 | O116: 46305
A117: 0040000090 | B117: C000070 | C117: BR004 | D117: SAV01 | E117: MMK | F117: Active | G117: 45729 | L117: 328076 | M117: 323.5824 | N117: 46307 | O117: 46271
A118: 0040000100 | B118: C000078 | C118: BR004 | D118: SAV01 | E118: MMK | F118: Active | G118: 44348 | L118: 7576098 | M118: 8688.2004 | N118: 46307 | O118: 46304
A119: 0040000126 | B119: C000100 | C119: BR004 | D119: SAV02 | E119: MMK | F119: Active | G119: 44301 | L119: 6633046 | M119: 7598.5952 | N119: 46307 | O119: 46307
A120: 0040000135 | B120: C000107 | C120: BR004 | D120: SAV01 | E120: MMK | F120: Active | G120: 46280 | L120: 96657 | M120: 260.9297 | N120: 46307 | O120: 46304
... A123: 0040000152 | B123: C000122 | C123: BR004 | D123: SAV01 | E123: MMK | F123: Frozen | G123: 46002 | L123: 1295748 | M123: 1490.9976 | N123: 46307 | O123: 46225
A124: 0040000156 | B124: C000125 | C124: BR004 | D124: SAV01 | E124: MMK | F124: Closed | G124: 45862 | L124: 0 | M124: 0 | O124: 46263 | P124: 46263
A125: 0040000168 | B125: C000134 | C125: BR004 | D125: CUR02 | E125: MMK | F125: Active | G125: 44677 | L125: 6599272 | M125: 0 | N125: 46307 | O125: 46296
A126: 0040000169 | B126: C000134 | C126: BR004 | D126: SAV01 | E126: MMK | F126: Active | G126: 44962 | L126: 2543060 | M126: 2926.2612 | N126: 46307 | O126: 46218
A127: 0040000174 | B127: C000138 | C127: BR004 | D127: SAV02 | E127: MMK | F127: Active | G127: 46181 | L127: 7846324 | M127: 11722.971 | N127: 46307 | O127: 46299
A128: 0040000178 | B128: C000141 | C128: BR004 | D128: SAV01 | E128: MMK | F128: Active | G128: 45171 | L128: 168069 | M128: 214.7626 | N128: 46307 | O128: 46303
A129: 0040000179 | B129: C000141 | C129: BR004 | D129: CUR01 | E129: MMK | F129: Active | G129: 44910 | L129: 1066794 | M129: 0 | N129: 46307 | O129: 46299
A130: 0040000190 | B130: C000151 | C130: BR004 | D130: SAV01 | E130: MMK | F130: Active | G130: 44825 | L130: 2172339 | M130: 2499.678 | N130: 46307 | O130: 46226
A131: 0040000206 | B131: C000165 | C131: BR004 | D131: SAV02 | E131: MMK | F131: Active | G131: 45925 | L131: 15672182 | M131: 22492.658 | N131: 46307 | O131: 46307
A132: 0040000207 | B132: C000165 | C132: BR004 | D132: CUR01 | E132: MMK | F132: Active | G132: 45576 | L132: 3899482 | M132: 0 | N132: 46307 | O132: 46304
A133: 0040000225 | B133: C000180 | C133: BR004 | D133: SAV01 | E133: MMK | F133: Active | G133: 45777 | L133: 592518 | M133: 872.9025 | N133: 46307 | O133: 46305
A134: 0040000237 | B134: C000189 | C134: BR004 | D134: SAV01 | E134: MMK | F134: Active | G134: 45736 | L134: 2632982 | M134: 2231.6537 | N134: 46307 | O134: 46305
A135: 0040000258 | B135: C000206 | C135: BR004 | D135: SAV01 | E135: MMK | F135: Active | G135: 45749 | L135: 3462629 | M135: 4178.3496 | N135: 46307 | O135: 46302
A136: 0040000259 | B136: C000206 | C136: BR004 | D136: CUR01 | E136: MMK | F136: Active | G136: 45822 | L136: 4083167 | M136: 0 | N136: 46307 | O136: 46304
... A148: 0040000387 | B148: C000311 | C148: BR004 | D148: CUR01 | E148: MMK | F148: Active | G148: 46251 | L148: 273353 | M148: 0 | N148: 46307 | O148: 46254
A149: 0040000410 | B149: C000290 | C149: BR004 | D149: FD01 | E149: MMK | F149: Active | G149: 46286 | H149: 3 | I149: 46377 | J149: 0.06 | K149: 0040000363 | L149: 6299451 | M149: 22781.576 | N149: 46307 | O149: 46286
A150: 0040000427 | B150: C000121 | C150: BR004 | D150: FD01 | E150: MMK | F150: Active | G150: 46145 | H150: 12 | I150: 46510 | J150: 0.085 | K150: 0040000151 | L150: 3016273 | M150: 114494.42 | N150: 46307 | O150: 46145
A151: 0050000012 | B151: C000009 | C151: BR005 | D151: SAV01 | E151: MMK | F151: Active | G151: 45142 | L151: 2577035 | M151: 1682.8703 | N151: 46307 | O151: 46305
A152: 0050000019 | B152: C000014 | C152: BR005 | D152: SAV01 | E152: MMK | F152: Active | G152: 45006 | L152: 48306 | M152: 85.4248 | N152: 46307 | O152: 46304
A153: 0050000020 | B153: C000014 | C153: BR005 | D153: CUR01 | E153: MMK | F153: Active | G153: 45015 | L153: 606153 | M153: 0 | N153: 46307 | O153: 46218
A154: 0050000039 | B154: C000031 | C154: BR005 | D154: SAV01 | E154: MMK | F154: Active | G154: 45355 | L154: 1308266 | M154: 1424.5557 | N154: 46307 | O154: 46307
A155: 0050000040 | B155: C000032 | C155: BR005 | D155: SAV01 | E155: MMK | F155: Active | G155: 45434 | L155: 1280243 | M155: 1634.0563 | N155: 46307 | O155: 46303
A156: 0050000042 | B156: C000034 | C156: BR005 | D156: SAV01 | E156: MMK | F156: Active | G156: 45583 | L156: 1148412 | M156: 864.4786 | N156: 46307 | O156: 46307
A157: 0050000080 | B157: C000063 | C157: BR005 | D157: SAV01 | E157: MMK | F157: Active | G157: 45185 | L157: 9186829 | M157: 8472.6819 | N157: 46307 | O157: 46305
A158: 0050000089 | B158: C000069 | C158: BR005 | D158: SAV01 | E158: MMK | F158: Active | G158: 44947 | L158: 1208685 | M158: 1206.4594 | N158: 46307 | O158: 46304
A159: 0050000099 | B159: C000077 | C159: BR005 | D159: CUR02 | E159: MMK | F159: Active | G159: 46177 | L159: 20522194 | M159: 3400.0617 | N159: 46307 | O159: 46303
...

Sheet Transactions
A1: TxnID | B1: GroupID | C1: TxnDate | D1: AccountNo | E1: TxnType | F1: Direction | G1: Amount | H1: BalanceAfter | I1: CounterAccountNo | J1: BranchID | K1: Description | L1: Reference | M1: JournalID | N1: Status | O1: CreatedBy | P1: ApprovedBy
A2: TX20260930-00001 | B2: G20260930-00001 | C2: 46295 | D2: 0010000009 | E2: Opening | F2: Credit | G2: 1602465 | H2: 1602465 | J2: BR001 | K2: Opening balance | M2: J00000017 | N2: Posted | O2: U001
A3: TX20260930-00002 | B3: G20260930-00001 | C3: 46295 | D3: 0010000010 | E3: Opening | F3: Credit | G3: 1167172 | H3: 1167172 | J3: BR001 | K3: Opening balance | M3: J00000017 | N3: Posted | O3: U001
A4: TX20260930-00003 | B4: G20260930-00001 | C4: 46295 | D4: 0010000011 | E4: Opening | F4: Credit | G4: 3940665 | H4: 3940665 | J4: BR001 | K4: Opening balance | M4: J00000017 | N4: Posted | O4: U001
A5: TX20260930-00004 | B5: G20260930-00001 | C5: 46295 | D5: 0010000024 | E5: Opening | F5: Credit | G5: 25028259 | H5: 25028259 | J5: BR001 | K5: Opening balance | M5: J00000017 | N5: Posted | O5: U001
A6: TX20260930-00005 | B6: G20260930-00001 | C6: 46295 | D6: 0010000025 | E6: Opening | F6: Credit | G6: 1712602 | H6: 1712602 | J6: BR001 | K6: Opening balance | M6: J00000017 | N6: Posted | O6: U001
A7: TX20260930-00006 | B7: G20260930-00001 | C7: 46295 | D7: 0010000031 | E7: Opening | F7: Credit | G7: 5000000 | H7: 5000000 | J7: BR001 | K7: Opening balance | M7: J00000017 | N7: Posted | O7: U001
A8: TX20260930-00007 | B8: G20260930-00001 | C8: 46295 | D8: 0010000036 | E8: Opening | F8: Credit | G8: 5612344 | H8: 5612344 | J8: BR001 | K8: Opening balance | M8: J00000017 | N8: Posted | O8: U001
A9: TX20260930-00008 | B9: G20260930-00001 | C9: 46295 | D9: 0010000076 | E9: Opening | F9: Credit | G9: 4688765 | H9: 4688765 | J9: BR001 | K9: Opening balance | M9: J00000017 | N9: Posted | O9: U001
A10: TX20260930-00009 | B10: G20260930-00001 | C10: 46295 | D10: 0010000092 | E10: Opening | F10: Credit | G10: 18143711 | H10: 18143711 | J10: BR001 | K10: Opening balance | M10: J00000017 | N10: Posted | O10: U001
A11: TX20260930-00010 | B11: G20260930-00001 | C11: 46295 | D11: 0010000120 | E11: Opening | F11: Credit | G11: 2387847 | H11: 2387847 | J11: BR001 | K11: Opening balance | M11: J00000017 | N11: Posted | O11: U001
A12: TX20260930-00011 | B12: G20260930-00001 | C12: 46295 | D12: 0010000130 | E12: Opening | F12: Credit | G12: 928543 | H12: 928543 | J12: BR001 | K12: Opening balance | M12: J00000017 | N12: Posted | O12: U001
A13: TX20260930-00012 | B13: G20260930-00001 | C13: 46295 | D13: 0010000131 | E13: Opening | F13: Credit | G13: 6778299 | H13: 6778299 | J13: BR001 | K13: Opening balance | M13: J00000017 | N13: Posted | O13: U001
... A463: TX20261001-00026 | B463: G20261001-00026 | C463: 46296 | D463: 0040000358 | E463: Withdrawal | F463: Debit | G463: 295764 | H463: 28572417 | J463: BR005 | K463: Cash withdrawal | M463: J00000058 | N463: Posted | O463: U017
A464: TX20261001-00027 | B464: G20261001-00026 | C464: 46296 | D464: 0040000358 | E464: Fee | F464: Debit | G464: 500 | H464: 28571917 | J464: BR005 | K464: Cross-branch cash withdrawal fee | L464: CROSS_BRANCH_WD | M464: J00000058 | N464: Posted | O464: U017
A465: TX20261001-00028 | B465: G20261001-00027 | C465: 46296 | D465: 0050000089 | E465: Withdrawal | F465: Debit | G465: 266313 | H465: 187543 | J465: BR005 | K465: Cash withdrawal | M465: J00000059 | N465: Posted | O465: U018
A466: TX20261001-00029 | B466: G20261001-00028 | C466: 46296 | D466: 0070000249 | E466: Withdrawal | F466: Debit | G466: 597948 | H466: 2418632 | J466: BR007 | K466: Cash withdrawal | M466: J00000060 | N466: Posted | O466: U024
A467: TX20261001-00030 | B467: G20261001-00029 | C467: 46296 | D467: 0030000107 | E467: Withdrawal | F467: Debit | G467: 211968 | H467: 2044111 | J467: BR003 | K467: Cash withdrawal | M467: J00000061 | N467: Posted | O467: U011
A468: TX20261001-00031 | B468: G20261001-00030 | C468: 46296 | D468: 0130000361 | E468: Withdrawal | F468: Debit | G468: 1805446 | H468: 7439744 | J468: BR013 | K468: Cash withdrawal | M468: J00000062 | N468: Posted | O468: U041
A469: TX20261001-00032 | B469: G20261001-00031 | C469: 46296 | D469: 0090000021 | E469: Withdrawal | F469: Debit | G469: 113728 | H469: 14316854 | J469: BR009 | K469: Cash withdrawal | M469: J00000063 | N469: Posted | O469: U029
A470: TX20261001-00033 | B470: G20261001-00032 | C470: 46296 | D470: 0010000131 | E470: Withdrawal | F470: Debit | G470: 2851017 | H470: 3927282 | J470: BR001 | K470: Cash withdrawal | M470: J00000064 | N470: Posted | O470: U005
A471: TX20261001-00034 | B471: G20261001-00033 | C471: 46296 | D471: 0060000369 | E471: Withdrawal | F471: Debit | G471: 622753 | H471: 425170 | J471: BR006 | K471: Cash withdrawal | M471: J00000065 | N471: Posted | O471: U020
A472: TX20261001-00035 | B472: G20261001-00034 | C472: 46296 | D472: 0040000168 | E472: Withdrawal | F472: Debit | G472: 2624751 | H472: 5975132 | J472: BR004 | K472: Cash withdrawal | M472: J00000066 | N472: Posted | O472: U014
A473: TX20261001-00036 | B473: G20261001-00035 | C473: 46296 | D473: 0060000095 | E473: Withdrawal | F473: Debit | G473: 532362 | H473: 364908 | J473: BR006 | K473: Cash withdrawal | M473: J00000067 | N473: Posted | O473: U020
A474: TX20261001-00037 | B474: G20261001-00036 | C474: 46296 | D474: 0060000365 | E474: Withdrawal | F474: Debit | G474: 401172 | H474: 788014 | J474: BR006 | K474: Cash withdrawal | M474: J00000068 | N474: Posted | O474: U020
A475: TX20261001-00038 | B475: G20261001-00037 | C475: 46296 | D475: 0090000195 | E475: TransferOut | F475: Debit | G475: 240695 | H475: 1403290 | I475: 0070000173 | J475: BR009 | K475: Transfer | M475: J00000069 | N475: Posted | O475: U030
A476: TX20261001-00039 | B476: G20261001-00037 | C476: 46296 | D476: 0090000195 | E476: Fee | F476: Debit | G476: 300 | H476: 1402990 | J476: BR009 | K476: Branch transfer fee | L476: TRANSFER_BRANCH | M476: J00000069 | N476: Posted | O476: U030
A477: TX20261001-00040 | B477: G20261001-00037 | C477: 46296 | D477: 0070000173 | E477: TransferIn | F477: Credit | G477: 240695 | H477: 7258206 | I477: 0090000195 | J477: BR009 | K477: Transfer | M477: J00000069 | N477: Posted | O477: U030
A478: TX20261001-00041 | B478: G20261001-00038 | C478: 46296 | D478: 0040000207 | E478: TransferOut | F478: Debit | G478: 75480 | H478: 3758522 | I478: 0060000393 | J478: BR004 | K478: Transfer | M478: J00000070 | N478: Posted | O478: U015
A479: TX20261001-00042 | B479: G20261001-00038 | C479: 46296 | D479: 0040000207 | E479: Fee | F479: Debit | G479: 300 | H479: 3758222 | J479: BR004 | K479: Branch transfer fee | L479: TRANSFER_BRANCH | M479: J00000070 | N479: Posted | O479: U015
A480: TX20261001-00043 | B480: G20261001-00038 | C480: 46296 | D480: 0060000393 | E480: TransferIn | F480: Credit | G480: 75480 | H480: 1200355 | I480: 0040000207 | J480: BR004 | K480: Transfer | M480: J00000070 | N480: Posted | O480: U015
A481: TX20261001-00044 | B481: G20261001-00039 | C481: 46296 | D481: 0080000162 | E481: TransferOut | F481: Debit | G481: 689179 | H481: 5887611 | I481: 0090000332 | J481: BR008 | K481: Transfer | M481: J00000071 | N481: Posted | O481: U026
A482: TX20261001-00045 | B482: G20261001-00039 | C482: 46296 | D482: 0080000162 | E482: Fee | F482: Debit | G482: 345 | H482: 5887266 | J482: BR008 | K482: Branch transfer fee | L482: TRANSFER_BRANCH | M482: J00000071 | N482: Posted | O482: U026
A483: TX20261001-00046 | B483: G20261001-00039 | C483: 46296 | D483: 0090000332 | E483: TransferIn | F483: Credit | G483: 689179 | H483: 1734043 | I483: 0080000162 | J483: BR008 | K483: Transfer | M483: J00000071 | N483: Posted | O483: U026
A484: TX20261001-00047 | B484: G20261001-00040 | C484: 46296 | D484: 0140000290 | E484: TransferOut | F484: Debit | G484: 321561 | H484: 35397004 | I484: 0070000333 | J484: BR014 | K484: Transfer | M484: J00000072 | N484: Posted | O484: U044
A485: TX20261001-00048 | B485: G20261001-00040 | C485: 46296 | D485: 0140000290 | E485: Fee | F485: Debit | G485: 300 | H485: 35396704 | J485: BR014 | K485: Branch transfer fee | L485: TRANSFER_BRANCH | M485: J00000072 | N485: Posted | O485: U044
A486: TX20261001-00049 | B486: G20261001-00040 | C486: 46296 | D486: 0070000333 | E486: TransferIn | F486: Credit | G486: 321561 | H486: 1841880 | I486: 0140000290 | J486: BR014 | K486: Transfer | M486: J00000072 | N486: Posted | O486: U044
A487: TX20261001-00050 | B487: G20261001-00041 | C487: 46296 | D487: 0030000254 | E487: TransferOut | F487: Debit | G487: 167428 | H487: 2196815 | I487: 0030000390 | J487: BR003 | K487: Transfer | M487: J00000073 | N487: Posted | O487: U011
A488: TX20261001-00051 | B488: G20261001-00041 | C488: 46296 | D488: 0030000390 | E488: TransferIn | F488: Credit | G488: 167428 | H488: 3746039 | I488: 0030000254 | J488: BR003 | K488: Transfer | M488: J00000073 | N488: Posted | O488: U011
A489: TX20261001-00052 | B489: G20261001-00042 | C489: 46296 | D489: 0150000303 | E489: TransferOut | F489: Debit | G489: 441790 | H489: 1441790 | I489: 0030000245 | J489: BR015 | K489: Transfer | M489: J00000074 | N489: Posted | O489: U047
A490: TX20261001-00053 | B490: G20261001-00042 | C490: 46296 | D490: 0150000303 | E490: Fee | F490: Debit | G490: 300 | H490: 1441490 | J490: BR015 | K490: Branch transfer fee | L490: TRANSFER_BRANCH | M490: J00000074 | N490: Posted | O490: U047
A491: TX20261001-00054 | B491: G20261001-00042 | C491: 46296 | D491: 0030000245 | E491: TransferIn | F491: Credit | G491: 441790 | H491: 4978013 | I491: 0150000303 | J491: BR015 | K491: Transfer | M491: J00000074 | N491: Posted | O491: U047
A492: TX20261001-00055 | B492: G20261001-00043 | C492: 46296 | D492: 0020000085 | E492: TransferOut | F492: Debit | G492: 219092 | H492: 41109620 | I492: 0010000244 | J492: BR002 | K492: Transfer | M492: J00000075 | N492: Posted | O492: U008
A493: TX20261001-00056 | B493: G20261001-00043 | C493: 46296 | D493: 0020000085 | E493: Fee | F493: Debit | G493: 300 | H493: 41109320 | J493: BR002 | K493: Branch transfer fee | L493: TRANSFER_BRANCH | M493: J00000075 | N493: Posted | O493: U008
A494: TX20261001-00057 | B494: G20261001-00043 | C494: 46296 | D494: 0010000244 | E494: TransferIn | F494: Credit | G494: 219092 | H494: 21517880 | I494: 0020000085 | J494: BR002 | K494: Transfer | M494: J00000075 | N494: Posted | O494: U008
A495: TX20261001-00058 | B495: G20261001-00044 | C495: 46296 | D495: 0030000231 | E495: TransferOut | F495: Debit | G495: 456560 | H495: 15761247 | I495: 0090000307 | J495: BR003 | K495: Transfer | M495: J00000076 | N495: Posted | O495: U012
A496: TX20261001-00059 | B496: G20261001-00044 | C496: 46296 | D496: 0030000231 | E496: Fee | F496: Debit | G496: 300 | H496: 15760947 | J496: BR003 | K496: Branch transfer fee | L496: TRANSFER_BRANCH | M496: J00000076 | N496: Posted | O496: U012
A497: TX20261001-00060 | B497: G20261001-00044 | C497: 46296 | D497: 0090000307 | E497: TransferIn | F497: Credit | G497: 456560 | H497: 4484128 | I497: 0030000231 | J497: BR003 | K497: Transfer | M497: J00000076 | N497: Posted | O497: U012
A498: TX20261001-00061 | B498: G20261001-00045 | C498: 46296 | D498: 0050000012 | E498: TransferOut | F498: Debit | G498: 480199 | H498: 629597 | I498: 0060000003 | J498: BR005 | K498: Transfer | M498: J00000077 | N498: Posted | O498: U018
A499: TX20261001-00062 | B499: G20261001-00045 | C499: 46296 | D499: 0050000012 | E499: Fee | F499: Debit | G499: 300 | H499: 629297 | J499: BR005 | K499: Branch transfer fee | L499: TRANSFER_BRANCH | M499: J00000077 | N499: Posted | O499: U018
A500: TX20261001-00063 | B500: G20261001-00045 | C500: 46296 | D500: 0060000003 | E500: TransferIn | F500: Credit | G500: 480199 | H500: 749089 | I500: 0050000012 | J500: BR005 | K500: Transfer | M500: J00000077 | N500: Posted | O500: U018
A501: TX20261001-00064 | B501: G20261001-00046 | C501: 46296 | D501: 0090000021 | E501: TransferOut | F501: Debit | G501: 1069571 | H501: 13247283 | I501: 0140000050 | J501: BR009 | K501: Transfer | M501: J00000078 | N501: Posted | O501: U029
A502: TX20261001-00065 | B502: G20261001-00046 | C502: 46296 | D502: 0090000021 | E502: Fee | F502: Debit | G502: 535 | H502: 13246748 | J502: BR009 | K502: Branch transfer fee | L502: TRANSFER_BRANCH | M502: J00000078 | N502: Posted | O502: U029
A503: TX20261001-00066 | B503: G20261001-00046 | C503: 46296 | D503: 0140000050 | E503: TransferIn | F503: Credit | G503: 1069571 | H503: 1273917 | I503: 0090000021 | J503: BR009 | K503: Transfer | M503: J00000078 | N503: Posted | O503: U029
A504: TX20261001-00067 | B504: G20261001-00047 | C504: 46296 | D504: 0030000375 | E504: InterbankOut | F504: Debit | G504: 156047 | H504: 244072 | I504: OB01 | J504: BR003 | K504: To Sunrise Commercial Bank (simulated) | M504: J00000079 | N504: Posted | O504: U011
A505: TX20261001-00068 | B505: G20261001-00047 | C505: 46296 | D505: 0030000375 | E505: Fee | F505: Debit | G505: 1000 | H505: 243072 | J505: BR003 | K505: Interbank transfer fee | L505: INTERBANK_OUT | M505: J00000079 | N505: Posted | O505: U011
A506: TX20261001-00069 | B506: G20261001-00048 | C506: 46296 | D506: 0040000168 | E506: InterbankIn | F506: Credit | G506: 624140 | H506: 6599272 | I506: OB03 | J506: BR004 | K506: From Delta Savings Bank (simulated) | M506: J00000080 | N506: Posted | O506: U002
A507: TX20261002-00001 | B507: G20261002-00001 | C507: 46297 | D507: 0060000440 | E507: Deposit | F507: Credit | G507: 929250 | H507: 929250 | J507: BR006 | K507: Opening deposit for new account | M507: J00000081 | N507: Posted | O507: U020
A508: TX20261002-00002 | B508: G20261002-00002 | C508: 46297 | D508: 0120000129 | E508: Deposit | F508: Credit | G508: 371027 | H508: 1272497 | J508: BR012 | K508: Cash deposit | M508: J00000082 | N508: Posted | O508: U039
A509: TX20261002-00003 | B509: G20261002-00003 | C509: 46297 | D509: 0040000062 | E509: Deposit | F509: Credit | G509: 919794 | H509: 2417566 | J509: BR004 | K509: Cash deposit | M509: J00000083 | N509: Posted | O509: U014
A510: TX20261002-00004 | B510: G20261002-00004 | C510: 46297 | D510: 0010000313 | E510: Deposit | F510: Credit | G510: 475488 | H510: 2267906 | J510: BR001 | K510: Cash deposit | M510: J00000084 | N510: Posted | O510: U005
A511: TX20261002-00005 | B511: G20261002-00005 | C511: 46297 | D511: 0040000293 | E511: Deposit | F511: Credit | G511: 68447 | H511: 1171584 | J511: BR003 | K511: Cash deposit | M511: J00000085 | N511: Posted | O511: U012
A512: TX20261002-00006 | B512: G20261002-00006 | C512: 46297 | D512: 0040000008 | E512: Deposit | F512: Credit | G512: 229396 | H512: 3023404 | J512: BR004 | K512: Cash deposit | M512: J00000086 | N512: Posted | O512: U015
A513: TX20261002-00007 | B513: G20261002-00007 | C513: 46297 | D513: 0050000202 | E513: Deposit | F513: Credit | G513: 904169 | H513: 11209053 | J513: BR005 | K513: Cash deposit | M513: J00000087 | N513: Posted | O513: U017
A514: TX20261002-00008 | B514: G20261002-00008 | C514: 46297 | D514: 0150000372 | E514: Deposit | F514: Credit | G514: 702142 | H514: 23158829 | J514: BR007 | K514: Cash deposit | M514: J00000088 | N514: Posted | O514: U024
A515: TX20261002-00009 | B515: G20261002-00009 | C515: 46297 | D515: 0040000342 | E515: Deposit | F515: Credit | G515: 1377805 | H515: 1949098 | J515: BR004 | K515: Cash deposit | M515: J00000089 | N515: Posted | O515: U014
A516: TX20261002-00010 | B516: G20261002-00010 | C516: 46297 | D516: 0080000054 | E516: Deposit | F516: Credit | G516: 4900000 | H516: 28156564 | J516: BR008 | K516: Cash deposit | M516: J00000090 | N516: Posted | O516: U027
A517: TX20261002-00011 | B517: G20261002-00011 | C517: 46297 | D517: 0120000157 | E517: Deposit | F517: Credit | G517: 493895 | H517: 1414675 | J517: BR012 | K517: Cash deposit | M517: J00000091 | N517: Posted | O517: U038
A518: TX20261002-00012 | B518: G20261002-00012 | C518: 46297 | D518: 0050000382 | E518: Deposit | F518: Credit | G518: 666320 | H518: 923526 | J518: BR005 | K518: Cash deposit | M518: J00000092 | N518: Posted | O518: U017
... A551: TX20261002-00045 | B551: G20261002-00045 | C551: 46297 | D551: 0030000016 | E551: Withdrawal | F551: Debit | G551: 3000000 | H551: 4034749 | J551: BR008 | K551: Cash withdrawal | M551: J00000125 | N551: Posted | O551: U027
A552: TX20261002-00046 | B552: G20261002-00045 | C552: 46297 | D552: 0030000016 | E552: Fee | F552: Debit | G552: 3000 | H552: 4031749 | J552: BR008 | K552: Cross-branch cash withdrawal fee | L552: CROSS_BRANCH_WD | M552: J00000125 | N552: Posted | O552: U027
A553: TX20261002-00047 | B553: G20261002-00046 | C553: 46297 | D553: 0080000324 | E553: Withdrawal | F553: Debit | G553: 465729 | H553: 1367831 | J553: BR008 | K553: Cash withdrawal | M553: J00000126 | N553: Posted | O553: U027
A554: TX20261002-00048 | B554: G20261002-00047 | C554: 46297 | D554: 0090000306 | E554: Withdrawal | F554: Debit | G554: 423137 | H554: 375212 | J554: BR009 | K554: Cash withdrawal | M554: J00000127 | N554: Posted | O554: U029
A555: TX20261002-00049 | B555: G20261002-00048 | C555: 46297 | D555: 0060000233 | E555: Withdrawal | F555: Debit | G555: 141329 | H555: 10581834 | J555: BR006 | K555: Cash withdrawal | M555: J00000128 | N555: Posted | O555: U020
A556: TX20261002-00050 | B556: G20261002-00049 | C556: 46297 | D556: 0120000325 | E556: Withdrawal | F556: Debit | G556: 143221 | H556: 907696 | J556: BR012 | K556: Cash withdrawal | M556: J00000129 | N556: Posted | O556: U039
A557: TX20261002-00051 | B557: G20261002-00050 | C557: 46297 | D557: 0060000007 | E557: Withdrawal | F557: Debit | G557: 144098 | H557: 196066 | J557: BR003 | K557: Cash withdrawal | M557: J00000130 | N557: Posted | O557: U011
A558: TX20261002-00052 | B558: G20261002-00050 | C558: 46297 | D558: 0060000007 | E558: Fee | F558: Debit | G558: 500 | H558: 195566 | J558: BR003 | K558: Cross-branch cash withdrawal fee | L558: CROSS_BRANCH_WD | M558: J00000130 | N558: Posted | O558: U011
A559: TX20261002-00053 | B559: G20261002-00051 | C559: 46297 | D559: 0040000358 | E559: TransferOut | F559: Debit | G559: 2000000 | H559: 26571917 | I559: 0070000286 | J559: BR004 | K559: Transfer | M559: J00000131 | N559: Posted | O559: U014
A560: TX20261002-00054 | B560: G20261002-00051 | C560: 46297 | D560: 0040000358 | E560: Fee | F560: Debit | G560: 1000 | H560: 26570917 | J560: BR004 | K560: Branch transfer fee | L560: TRANSFER_BRANCH | M560: J00000131 | N560: Posted | O560: U014
A561: TX20261002-00055 | B561: G20261002-00051 | C561: 46297 | D561: 0070000286 | E561: TransferIn | F561: Credit | G561: 2000000 | H561: 30674186 | I561: 0040000358 | J561: BR004 | K561: Transfer | M561: J00000131 | N561: Posted | O561: U014
A562: TX20261002-00056 | B562: G20261002-00052 | C562: 46297 | D562: 0050000040 | E562: TransferOut | F562: Debit | G562: 25831 | H562: 1516518 | I562: 0130000081 | J562: BR005 | K562: Transfer | M562: J00000132 | N562: Posted | O562: U018
A563: TX20261002-00057 | B563: G20261002-00052 | C563: 46297 | D563: 0050000040 | E563: Fee | F563: Debit | G563: 300 | H563: 1516218 | J563: BR005 | K563: Branch transfer fee | L563: TRANSFER_BRANCH | M563: J00000132 | N563: Posted | O563: U018
A564: TX20261002-00058 | B564: G20261002-00052 | C564: 46297 | D564: 0130000081 | E564: TransferIn | F564: Credit | G564: 25831 | H564: 1266480 | I564: 0050000040 | J564: BR005 | K564: Transfer | M564: J00000132 | N564: Posted | O564: U018
A565: TX20261002-00059 | B565: G20261002-00053 | C565: 46297 | D565: 0010000321 | E565: TransferOut | F565: Debit | G565: 258329 | H565: 3228286 | I565: 0050000012 | J565: BR001 | K565: Transfer | M565: J00000133 | N565: Posted | O565: U005
A566: TX20261002-00060 | B566: G20261002-00053 | C566: 46297 | D566: 0010000321 | E566: Fee | F566: Debit | G566: 300 | H566: 3227986 | J566: BR001 | K566: Branch transfer fee | L566: TRANSFER_BRANCH | M566: J00000133 | N566: Posted | O566: U005
A567: TX20261002-00061 | B567: G20261002-00053 | C567: 46297 | D567: 0050000012 | E567: TransferIn | F567: Credit | G567: 258329 | H567: 887626 | I567: 0010000321 | J567: BR001 | K567: Transfer | M567: J00000133 | N567: Posted | O567: U005
A568: TX20261002-00062 | B568: G20261002-00054 | C568: 46297 | D568: 0070000105 | E568: TransferOut | F568: Debit | G568: 90190 | H568: 100190 | I568: 0030000091 | J568: BR007 | K568: Transfer | M568: J00000134 | N568: Posted | O568: U023
A569: TX20261002-00063 | B569: G20261002-00054 | C569: 46297 | D569: 0070000105 | E569: Fee | F569: Debit | G569: 300 | H569: 99890 | J569: BR007 | K569: Branch transfer fee | L569: TRANSFER_BRANCH | M569: J00000134 | N569: Posted | O569: U023
A570: TX20261002-00064 | B570: G20261002-00054 | C570: 46297 | D570: 0030000091 | E570: TransferIn | F570: Credit | G570: 90190 | H570: 1523400 | I570: 0070000105 | J570: BR007 | K570: Transfer | M570: J00000134 | N570: Posted | O570: U023
A571: TX20261002-00065 | B571: G20261002-00055 | C571: 46297 | D571: 0010000256 | E571: TransferOut | F571: Debit | G571: 101268 | H571: 816030 | I571: 0120000215 | J571: BR001 | K571: Transfer | M571: J00000135 | N571: Posted | O571: U006
A572: TX20261002-00066 | B572: G20261002-00055 | C572: 46297 | D572: 0010000256 | E572: Fee | F572: Debit | G572: 300 | H572: 815730 | J572: BR001 | K572: Branch transfer fee | L572: TRANSFER_BRANCH | M572: J00000135 | N572: Posted | O572: U006
A573: TX20261002-00067 | B573: G20261002-00055 | C573: 46297 | D573: 0120000215 | E573: TransferIn | F573: Credit | G573: 101268 | H573: 14567909 | I573: 0010000256 | J573: BR001 | K573: Transfer | M573: J00000135 | N573: Posted | O573: U006
A574: TX20261002-00068 | B574: G20261002-00056 | C574: 46297 | D574: 0020000136 | E574: TransferOut | F574: Debit | G574: 1130863 | H574: 38883764 | I574: 0060000391 | J574: BR002 | K574: Transfer | M574: J00000136 | N574: Posted | O574: U008
A575: TX20261002-00069 | B575: G20261002-00056 | C575: 46297 | D575: 0020000136 | E575: Fee | F575: Debit | G575: 565 | H575: 38883199 | J575: BR002 | K575: Branch transfer fee | L575: TRANSFER_BRANCH | M575: J00000136 | N575: Posted | O575: U008
A576: TX20261002-00070 | B576: G20261002-00056 | C576: 46297 | D576: 0060000391 | E576: TransferIn | F576: Credit | G576: 1130863 | H576: 13221168 | I576: 0020000136 | J576: BR002 | K576: Transfer | M576: J00000136 | N576: Posted | O576: U008
A577: TX20261002-00071 | B577: G20261002-00057 | C577: 46297 | D577: 0140000326 | E577: InterbankOut | F577: Debit | G577: 332157 | H577: 508237 | I577: OB02 | J577: BR014 | K577: To Golden River Bank (simulated) | M577: J00000137 | N577: Posted | O577: U044
A578: TX20261002-00072 | B578: G20261002-00057 | C578: 46297 | D578: 0140000326 | E578: Fee | F578: Debit | G578: 1000 | H578: 507237 | J578: BR014 | K578: Interbank transfer fee | L578: INTERBANK_OUT | M578: J00000137 | N578: Posted | O578: U044
A579: TX20261002-00073 | B579: G20261002-00058 | C579: 46297 | D579: 0070000250 | E579: InterbankOut | F579: Debit | G579: 388239 | H579: 3938688 | I579: OB04 | J579: BR007 | K579: To Capital Trust Bank (simulated) | M579: J00000138 | N579: Posted | O579: U024
A580: TX20261002-00074 | B580: G20261002-00058 | C580: 46297 | D580: 0070000250 | E580: Fee | F580: Debit | G580: 1000 | H580: 3937688 | J580: BR007 | K580: Interbank transfer fee | L580: INTERBANK_OUT | M580: J00000138 | N580: Posted | O580: U024
A581: TX20261002-00075 | B581: G20261002-00059 | C581: 46297 | D581: 0020000350 | E581: InterbankOut | F581: Debit | G581: 373780 | H581: 570672 | I581: OB03 | J581: BR002 | K581: To Delta Savings Bank (simulated) | M581: J00000139 | N581: Posted | O581: U009
...

Sheet InterbankTransfers
A1: TransferID | B1: Direction | C1: AccountNo | D1: OtherBankCode | E1: OtherBankAccount | F1: Amount | G1: Fee | H1: SubmittedDate | I1: ExpectedSettleDate | J1: Status | K1: StatusDate | L1: Reason | M1: SubmitJournalID | N1: SettleJournalID | O1: ReturnJournalID
A2: IB000001 | B2: Out | C2: 0030000375 | D2: OB01 | E2: 1581409834 | F2: 156047 | G2: 1000 | H2: 46296 | I2: 46297 | J2: Returned | K2: 46304 | L2: Returned after settlement (simulated) | M2: J00000079 | N2: J00000141 | O2: J00000536
A3: IB000002 | B3: In | C3: 0040000168 | D3: OB03 | E3: 6898735050 | F3: 624140 | G3: 0 | H3: 46296 | I3: 46296 | J3: Settled | K3: 46296 | M3: J00000080
A4: IB000003 | B4: Out | C4: 0140000326 | D4: OB02 | E4: 6152481848 | F4: 332157 | G4: 1000 | H4: 46297 | I4: 46299 | J4: Settled | K4: 46299 | M4: J00000137 | N4: J00000244
A5: IB000004 | B5: Out | C5: 0070000250 | D5: OB04 | E5: 5018109944 | F5: 388239 | G5: 1000 | H5: 46297 | I5: 46298 | J5: Settled | K5: 46298 | M5: J00000138 | N5: J00000192
A6: IB000005 | B6: Out | C6: 0020000350 | D6: OB03 | E6: 6065832573 | F6: 373780 | G6: 1000 | H6: 46297 | I6: 46299 | J6: Settled | K6: 46299 | M6: J00000139 | N6: J00000245
A7: IB000006 | B7: In | C7: 0030000254 | D7: OB03 | E7: 2685210444 | F7: 226589 | G7: 0 | H7: 46297 | I7: 46297 | J7: Settled | K7: 46297 | M7: J00000140
A8: IB000007 | B8: Out | C8: 0060000158 | D8: OB02 | E8: 8940288772 | F8: 232598 | G8: 1000 | H8: 46298 | I8: 46300 | J8: Settled | K8: 46300 | M8: J00000187 | N8: J00000305
A9: IB000008 | B9: Out | C9: 0150000305 | D9: OB03 | E9: 4159874018 | F9: 320905 | G9: 1000 | H9: 46298 | I9: 46300 | J9: Failed | K9: 46300 | L9: Rejected by receiving bank (simulated) | M9: J00000188 | N9: J00000306
A10: IB000009 | B10: In | C10: 0030000015 | D10: OB01 | E10: 6090559763 | F10: 348198 | G10: 0 | H10: 46298 | I10: 46298 | J10: Settled | K10: 46298 | M10: J00000189
A11: IB000010 | B11: In | C11: 0080000373 | D11: OB03 | E11: 6536532038 | F11: 159537 | G11: 0 | H11: 46298 | I11: 46298 | J11: Settled | K11: 46298 | M11: J00000190
A12: IB000011 | B12: Out | C12: 0090000332 | D12: OB01 | E12: 3739797135 | F12: 309898 | G12: 1000 | H12: 46299 | I12: 46300 | J12: Settled | K12: 46300 | M12: J00000240 | N12: J00000307
A13: IB000012 | B13: Out | C13: 0020000276 | D13: OB01 | E13: 8825064736 | F13: 455774 | G13: 1000 | H13: 46299 | I13: 46300 | J13: Settled | K13: 46300 | M13: J00000241 | N13: J00000308
A14: IB000013 | B14: In | C14: 0130000288 | D14: OB04 | E14: 3025221142 | F14: 229992 | G14: 0 | H14: 46299 | I14: 46299 | J14: Settled | K14: 46299 | M14: J00000242
A15: IB000014 | B15: In | C15: 0120000157 | D15: OB04 | E15: 7507708782 | F15: 2314946 | G15: 0 | H15: 46299 | I15: 46299 | J15: Settled | K15: 46299 | M15: J00000243
A16: IB000015 | B16: Out | C16: 0080000294 | D16: OB04 | E16: 1807286349 | F16: 984188 | G16: 1000 | H16: 46300 | I16: 46301 | J16: Settled | K16: 46301 | M16: J00000302 | N16: J00000365
A17: IB000016 | B17: Out | C17: 0020000308 | D17: OB04 | E17: 6275845655 | F17: 441253 | G17: 1000 | H17: 46300 | I17: 46301 | J17: Settled | K17: 46301 | M17: J00000303 | N17: J00000366
A18: IB000017 | B18: In | C18: 0030000180 | D18: OB04 | E18: 1258613570 | F18: 1259598 | G18: 0 | H18: 46300 | I18: 46300 | J18: Settled | K18: 46300 | M18: J00000304
A19: IB000018 | B19: Out | C19: 0140000264 | D19: OB02 | E19: 9431608213 | F19: 223620 | G19: 1000 | H19: 46301 | I19: 46303 | J19: Settled | K19: 46303 | M19: J00000362 | N19: J00000480
A20: IB000019 | B20: Out | C20: 0060000154 | D20: OB02 | E20: 4153152075 | F20: 191077 | G20: 1000 | H20: 46301 | I20: 46303 | J20: Settled | K20: 46303 | M20: J00000363 | N20: J00000481
A21: IB000020 | B21: Out | C21: 0020000136 | D21: OB04 | E21: 4031248076 | F21: 248744 | G21: 1000 | H21: 46301 | I21: 46302 | J21: Settled | K21: 46302 | M21: J00000364 | N21: J00000427
A22: IB000021 | B22: Out | C22: 0050000137 | D22: OB03 | E22: 3536743142 | F22: 246253 | G22: 1000 | H22: 46302 | I22: 46304 | J22: Settled | K22: 46304 | M22: J00000423 | N22: J00000533
A23: IB000022 | B23: Out | C23: 0050000345 | D23: OB02 | E23: 2472670161 | F23: 149635 | G23: 1000 | H23: 46302 | I23: 46304 | J23: Settled | K23: 46304 | M23: J00000424 | N23: J00000534
A24: IB000023 | B24: Out | C24: 0090000307 | D24: OB01 | E24: 6077331293 | F24: 65309 | G24: 1000 | H24: 46302 | I24: 46303 | J24: Settled | K24: 46303 | M24: J00000425 | N24: J00000482
A25: IB000024 | B25: Out | C25: 0020000263 | D25: OB02 | E25: 6447203358 | F25: 173562 | G25: 1000 | H25: 46303 | I25: 46305 | J25: Settled | K25: 46305 | M25: J00000476 | N25: J00000594
A26: IB000025 | B26: Out | C26: 0140000001 | D26: OB01 | E26: 1328214418 | F26: 246034 | G26: 1000 | H26: 46303 | I26: 46304 | J26: Settled | K26: 46304 | M26: J00000477 | N26: J00000535
A27: IB000026 | B27: In | C27: 0120000129 | D27: OB02 | E27: 2712969555 | F27: 965462 | G27: 0 | H27: 46303 | I27: 46303 | J27: Settled | K27: 46303 | M27: J00000478
A28: IB000027 | B28: In | C28: 0040000237 | D28: OB04 | E28: 1012554516 | F28: 2373951 | G28: 0 | H28: 46303 | I28: 46303 | J28: Settled | K28: 46303 | M28: J00000479
A29: IB000028 | B29: Out | C29: 0030000047 | D29: OB01 | E29: 7482342463 | F29: 161440 | G29: 1000 | H29: 46304 | I29: 46305 | J29: Settled | K29: 46305 | M29: J00000530 | N29: J00000595
A30: IB000029 | B30: In | C30: 0100000182 | D30: OB04 | E30: 5873669720 | F30: 329539 | G30: 0 | H30: 46304 | I30: 46304 | J30: Settled | K30: 46304 | M30: J00000531
A31: IB000030 | B31: In | C31: 0050000382 | D31: OB04 | E31: 4679989557 | F31: 1538808 | G31: 0 | H31: 46304 | I31: 46304 | J31: Settled | K31: 46304 | M31: J00000532
A32: IB000031 | B32: Out | C32: 0100000274 | D32: OB01 | E32: 2072382280 | F32: 615566 | G32: 1000 | H32: 46305 | I32: 46306 | J32: Settled | K32: 46306 | M32: J00000589 | N32: J00000646
A33: IB000032 | B33: Out | C33: 0040000225 | D33: OB04 | E33: 8668339000 | F33: 389011 | G33: 1000 | H33: 46305 | I33: 46306 | J33: Settled | K33: 46306 | M33: J00000590 | N33: J00000647
A34: IB000033 | B34: Out | C34: 0110000267 | D34: OB02 | E34: 4556962935 | F34: 222908 | G34: 1000 | H34: 46305 | I34: 46307 | J34: Settled | K34: 46307 | M34: J00000591 | N34: J00000702
A35: IB000034 | B35: In | C35: 0010000076 | D35: OB03 | E35: 3418264401 | F35: 387543 | G35: 0 | H35: 46305 | I35: 46305 | J35: Settled | K35: 46305 | M35: J00000592
A36: IB000035 | B36: Out | C36: 0070000087 | D36: OB02 | E36: 2831809487 | F36: 77411 | G36: 1000 | H36: 46306 | I36: 46308 | J36: Submitted | K36: 46306 | M36: J00000645
A37: IB000036 | B37: Out | C37: 0030000066 | D37: OB02 | E37: 8117199418 | F37: 349956 | G37: 1000 | H37: 46307 | I37: 46309 | J37: Submitted | K37: 46307 | M37: J00000701

Sheet Approvals
A1: ApprovalID | B1: RequestType | C1: AccountNo | D1: CounterAccountNo | E1: Amount | F1: BranchID | G1: Note | H1: RequestedBy | I1: RequestedAt | J1: Status | K1: ApprovedBy | L1: DecidedAt | M1: DecisionNote | N1: TxnGroupID
A2: AP000001 | B2: LargeDeposit | C2: 0100000283 | E2: 27000000 | F2: BR010 | G2: Sample largedeposit | H2: U032 | I2: 46298.411 | J2: Approved | K2: U034 | L2: 46298.456 | N2: G20261003-00050
A3: AP000002 | B3: LargeDeposit | C3: 0060000233 | E3: 15000000 | F3: BR006 | G3: Sample largedeposit | H3: U021 | I3: 46302.381 | J3: Approved | K3: U022 | L3: 46302.419 | N3: G20261007-00060
A4: AP000003 | B4: LargeDeposit | C4: 0040000340 | E4: 17000000 | F4: BR004 | G4: Sample largedeposit | H4: U015 | I4: 46305.401 | J4: Approved | K4: U016 | L4: 46305.431 | N4: G20261010-00057
A5: AP000004 | B5: Reversal | C5: 0050000443 | E5: 165108 | F5: BR005 | G5: Sample reversal | H5: U002 | I5: 46301.392 | J5: Approved | K5: U003 | L5: 46301.454 | N5: G20261006-00059
A6: AP000005 | B6: LargeWithdrawal | C6: 0020000002 | E6: 8000000 | F6: BR002 | G6: Sample largewithdrawal | H6: U008 | I6: 46307.407 | J6: Pending
A7: AP000006 | B7: LargeWithdrawal | C7: 0060000022 | E7: 8000000 | F7: BR006 | G7: Sample largewithdrawal | H7: U021 | I7: 46307.389 | J7: Pending
A8: AP000007 | B8: LargeTransfer | C8: 0020000002 | D8: 0040000017 | E8: 12000000 | F8: BR002 | G8: Sample largetransfer | H8: U009 | I8: 46307.409 | J8: Pending
A9: AP000008 | B9: CashShipment | E9: 200000000 | F9: BR012 | G9: Sample cashshipment | H9: U002 | I9: 46307.406 | J9: Pending
A10: AP000009 | B10: LargeWithdrawal | C10: 0030000045 | E10: 9000000 | F10: BR003 | G10: Sample largewithdrawal | H10: U012 | I10: 46304.415 | J10: Rejected | K10: U013 | L10: 46304.419 | M10: Customer could not show identification

Sheet Journal
A1: JournalID | B1: PostDate | C1: Description | D1: JournalType | E1: GroupID | F1: Status | G1: ReversalOf | H1: CreatedBy | I1: CreatedAt
A2: J00000001 | B2: 46295 | C2: Share capital paid in | D2: Opening | E2: G20260930-00001 | F2: Posted | H2: U001 | I2: 46295.685
A3: J00000002 | B3: 46295 | C3: Head office cash from treasury | D3: Opening | E3: G20260930-00001 | F3: Posted | H3: U001 | I3: 46295.572
A4: J00000003 | B4: 46295 | C4: Opening cash for Hlaing Branch | D4: Opening | E4: G20260930-00001 | F4: Posted | H4: U001 | I4: 46295.503
A5: J00000004 | B5: 46295 | C5: Opening cash for Thingangyun Branch | D5: Opening | E5: G20260930-00001 | F5: Posted | H5: U001 | I5: 46295.607
A6: J00000005 | B6: 46295 | C6: Opening cash for Chanayethazan Branch | D6: Opening | E6: G20260930-00001 | F6: Posted | H6: U001 | I6: 46295.605
A7: J00000006 | B7: 46295 | C7: Opening cash for Aungmyaythazan Branch | D7: Opening | E7: G20260930-00001 | F7: Posted | H7: U001 | I7: 46295.633
A8: J00000007 | B8: 46295 | C8: Opening cash for Zabuthiri Branch | D8: Opening | E8: G20260930-00001 | F8: Posted | H8: U001 | I8: 46295.61
A9: J00000008 | B9: 46295 | C9: Opening cash for Mawlamyine Branch | D9: Opening | E9: G20260930-00001 | F9: Posted | H9: U001 | I9: 46295.403
A10: J00000009 | B10: 46295 | C10: Opening cash for Taunggyi Branch | D10: Opening | E10: G20260930-00001 | F10: Posted | H10: U001 | I10: 46295.456
A11: J00000010 | B11: 46295 | C11: Opening cash for Pyin Oo Lwin Branch | D11: Opening | E11: G20260930-00001 | F11: Posted | H11: U001 | I11: 46295.393
A12: J00000011 | B12: 46295 | C12: Opening cash for Kyaukse Branch | D12: Opening | E12: G20260930-00001 | F12: Posted | H12: U001 | I12: 46295.574
A13: J00000012 | B13: 46295 | C13: Opening cash for Meiktila Branch | D13: Opening | E13: G20260930-00001 | F13: Posted | H13: U001 | I13: 46295.471
... A703: J00000702 | B703: 46307 | C703: Interbank settlement (simulated) | D703: InterbankSettle | E703: G20261012-00055 | F703: Posted | H703: U002 | I703: 46307.479
A704: J00000703 | B704: 46301 | C704: Reversal of TX20261005-00001 | D704: Reversal | E704: G20261006-00059 | F704: Posted | G704: J00000246 | H704: U002 | I704: 46301.662

Sheet JournalLines
A1: LineID | B1: JournalID | C1: BranchID | D1: GLCode | E1: AccountNo | F1: Currency | G1: Debit | H1: Credit | I1: FxRate | J1: ForeignAmount
A2: L0000001 | B2: J00000001 | C2: BR001 | D2: 1100 | F2: MMK | G2: 20000000000 | H2: 0
A3: L0000002 | B3: J00000001 | C3: BR001 | D3: 3000 | F3: MMK | G3: 0 | H3: 20000000000
A4: L0000003 | B4: J00000002 | C4: BR001 | D4: 1000 | F4: MMK | G4: 4500000000 | H4: 0
A5: L0000004 | B5: J00000002 | C5: BR001 | D5: 1100 | F5: MMK | G5: 0 | H5: 4500000000
A6: L0000005 | B6: J00000003 | C6: BR002 | D6: 1000 | F6: MMK | G6: 300000000 | H6: 0
A7: L0000006 | B7: J00000003 | C7: BR002 | D7: 1900 | F7: MMK | G7: 0 | H7: 300000000
A8: L0000007 | B8: J00000003 | C8: BR001 | D8: 1900 | F8: MMK | G8: 300000000 | H8: 0
A9: L0000008 | B9: J00000003 | C9: BR001 | D9: 1000 | F9: MMK | G9: 0 | H9: 300000000
A10: L0000009 | B10: J00000004 | C10: BR003 | D10: 1000 | F10: MMK | G10: 300000000 | H10: 0
A11: L0000010 | B11: J00000004 | C11: BR003 | D11: 1900 | F11: MMK | G11: 0 | H11: 300000000
A12: L0000011 | B12: J00000004 | C12: BR001 | D12: 1900 | F12: MMK | G12: 300000000 | H12: 0
A13: L0000012 | B13: J00000004 | C13: BR001 | D13: 1000 | F13: MMK | G13: 0 | H13: 300000000
... A61: L0000060 | B61: J00000016 | C61: BR001 | D61: 1000 | F61: MMK | G61: 0 | H61: 120000000
A62: L0000061 | B62: J00000017 | C62: BR001 | D62: 2000 | E62: 0010000009 | F62: MMK | G62: 0 | H62: 1602465
A63: L0000062 | B63: J00000017 | C63: BR001 | D63: 2010 | E63: 0010000010 | F63: MMK | G63: 0 | H63: 1167172
A64: L0000063 | B64: J00000017 | C64: BR001 | D64: 2000 | E64: 0010000011 | F64: MMK | G64: 0 | H64: 3940665
A65: L0000064 | B65: J00000017 | C65: BR001 | D65: 2010 | E65: 0010000024 | F65: MMK | G65: 0 | H65: 25028259
A66: L0000065 | B66: J00000017 | C66: BR001 | D66: 2000 | E66: 0010000025 | F66: MMK | G66: 0 | H66: 1712602
A67: L0000066 | B67: J00000017 | C67: BR001 | D67: 2000 | E67: 0010000031 | F67: MMK | G67: 0 | H67: 5000000
A68: L0000067 | B68: J00000017 | C68: BR001 | D68: 2000 | E68: 0010000036 | F68: MMK | G68: 0 | H68: 5612344
A69: L0000068 | B69: J00000017 | C69: BR001 | D69: 2000 | E69: 0010000076 | F69: MMK | G69: 0 | H69: 4688765
A70: L0000069 | B70: J00000017 | C70: BR001 | D70: 2010 | E70: 0010000092 | F70: MMK | G70: 0 | H70: 18143711
A71: L0000070 | B71: J00000017 | C71: BR001 | D71: 2000 | E71: 0010000120 | F71: MMK | G71: 0 | H71: 2387847
A72: L0000071 | B72: J00000017 | C72: BR001 | D72: 2000 | E72: 0010000130 | F72: MMK | G72: 0 | H72: 928543
A73: L0000072 | B73: J00000017 | C73: BR001 | D73: 2010 | E73: 0010000131 | F73: MMK | G73: 0 | H73: 6778299
... A87: L0000086 | B87: J00000017 | C87: BR001 | D87: 2020 | E87: 0010000422 | F87: MMK | G87: 0 | H87: 6675443
A88: L0000087 | B88: J00000017 | C88: BR001 | D88: 1900 | F88: MMK | G88: 152266065 | H88: 0
A89: L0000088 | B89: J00000018 | C89: BR002 | D89: 2010 | E89: 0020000002 | F89: MMK | G89: 0 | H89: 48110974
A90: L0000089 | B90: J00000018 | C90: BR002 | D90: 2000 | E90: 0020000005 | F90: MMK | G90: 0 | H90: 469866
A91: L0000090 | B91: J00000018 | C91: BR002 | D91: 2000 | E91: 0020000013 | F91: MMK | G91: 0 | H91: 558234
A92: L0000091 | B92: J00000018 | C92: BR002 | D92: 2000 | E92: 0020000030 | F92: MMK | G92: 0 | H92: 450886
A93: L0000092 | B93: J00000018 | C93: BR002 | D93: 2000 | E93: 0020000034 | F93: MMK | G93: 0 | H93: 302269
A94: L0000093 | B94: J00000018 | C94: BR002 | D94: 2000 | E94: 0020000041 | F94: MMK | G94: 0 | H94: 7479468
A95: L0000094 | B95: J00000018 | C95: BR002 | D95: 2000 | E95: 0020000069 | F95: MMK | G95: 0 | H95: 2874048
A96: L0000095 | B96: J00000018 | C96: BR002 | D96: 2010 | E96: 0020000070 | F96: MMK | G96: 0 | H96: 776704
A97: L0000096 | B97: J00000018 | C97: BR002 | D97: 2010 | E97: 0020000085 | F97: MMK | G97: 0 | H97: 41328712
A98: L0000097 | B98: J00000018 | C98: BR002 | D98: 2000 | E98: 0020000086 | F98: MMK | G98: 0 | H98: 1418364
A99: L0000098 | B99: J00000018 | C99: BR002 | D99: 2000 | E99: 0020000096 | F99: MMK | G99: 0 | H99: 11464349
A100: L0000099 | B100: J00000018 | C100: BR002 | D100: 2010 | E100: 0020000097 | F100: MMK | G100: 0 | H100: 7385210
... A121: L0000120 | B121: J00000018 | C121: BR002 | D121: 2020 | E121: 0020000423 | F121: MMK | G121: 0 | H121: 5664075
A122: L0000121 | B122: J00000018 | C122: BR002 | D122: 1900 | F122: MMK | G122: 330357367 | H122: 0
A123: L0000122 | B123: J00000019 | C123: BR003 | D123: 2000 | E123: 0030000015 | F123: MMK | G123: 0 | H123: 7677354
A124: L0000123 | B124: J00000019 | C124: BR003 | D124: 2010 | E124: 0030000016 | F124: MMK | G124: 0 | H124: 7034749
A125: L0000124 | B125: J00000019 | C125: BR003 | D125: 2000 | E125: 0030000033 | F125: MMK | G125: 0 | H125: 1108579
A126: L0000125 | B126: J00000019 | C126: BR003 | D126: 2010 | E126: 0030000045 | F126: MMK | G126: 0 | H126: 61344653
A127: L0000126 | B127: J00000019 | C127: BR003 | D127: 2000 | E127: 0030000046 | F127: MMK | G127: 0 | H127: 29433451
A128: L0000127 | B128: J00000019 | C128: BR003 | D128: 2000 | E128: 0030000047 | F128: MMK | G128: 0 | H128: 1075134
A129: L0000128 | B129: J00000019 | C129: BR003 | D129: 2010 | E129: 0030000057 | F129: MMK | G129: 0 | H129: 122125089
A130: L0000129 | B130: J00000019 | C130: BR003 | D130: 2000 | E130: 0030000065 | F130: MMK | G130: 0 | H130: 1849828
A131: L0000130 | B131: J00000019 | C131: BR003 | D131: 2010 | E131: 0030000066 | F131: MMK | G131: 0 | H131: 1594418
A132: L0000131 | B132: J00000019 | C132: BR003 | D132: 2010 | E132: 0030000072 | F132: MMK | G132: 0 | H132: 8079926
A133: L0000132 | B133: J00000019 | C133: BR003 | D133: 2000 | E133: 0030000073 | F133: MMK | G133: 0 | H133: 3797430
A134: L0000133 | B134: J00000019 | C134: BR003 | D134: 2000 | E134: 0030000077 | F134: MMK | G134: 0 | H134: 787375
... A168: L0000167 | B168: J00000019 | C168: BR003 | D168: 2020 | E168: 0030000438 | F168: MMK | G168: 0 | H168: 8820584
A169: L0000168 | B169: J00000019 | C169: BR003 | D169: 1900 | F169: MMK | G169: 397681605 | H169: 0
A170: L0000169 | B170: J00000020 | C170: BR004 | D170: 2010 | E170: 0040000008 | F170: MMK | G170: 0 | H170: 2794008
A171: L0000170 | B171: J00000020 | C171: BR004 | D171: 2000 | E171: 0040000017 | F171: MMK | G171: 0 | H171: 26160838
A172: L0000171 | B172: J00000020 | C172: BR004 | D172: 2010 | E172: 0040000018 | F172: MMK | G172: 0 | H172: 2762817
A173: L0000172 | B173: J00000020 | C173: BR004 | D173: 2000 | E173: 0040000028 | F173: MMK | G173: 0 | H173: 1331646
A174: L0000173 | B174: J00000020 | C174: BR004 | D174: 2000 | E174: 0040000062 | F174: MMK | G174: 0 | H174: 1497772
A175: L0000174 | B175: J00000020 | C175: BR004 | D175: 2010 | E175: 0040000063 | F175: MMK | G175: 0 | H175: 2344248
A176: L0000175 | B176: J00000020 | C176: BR004 | D176: 2010 | E176: 0040000071 | F176: MMK | G176: 0 | H176: 27923204
A177: L0000176 | B177: J00000020 | C177: BR004 | D177: 2000 | E177: 0040000090 | F177: MMK | G177: 0 | H177: 328076
A178: L0000177 | B178: J00000020 | C178: BR004 | D178: 2000 | E178: 0040000100 | F178: MMK | G178: 0 | H178: 7202923
A179: L0000178 | B179: J00000020 | C179: BR004 | D179: 2000 | E179: 0040000126 | F179: MMK | G179: 0 | H179: 5000000
A180: L0000179 | B180: J00000020 | C180: BR004 | D180: 2000 | E180: 0040000135 | F180: MMK | G180: 0 | H180: 551603
A181: L0000180 | B181: J00000020 | C181: BR004 | D181: 2000 | E181: 0040000150 | F181: MMK | G181: 0 | H181: 740293
... A209: L0000208 | B209: J00000020 | C209: BR004 | D209: 2020 | E209: 0040000427 | F209: MMK | G209: 0 | H209: 3016273
A210: L0000209 | B210: J00000020 | C210: BR004 | D210: 1900 | F210: MMK | G210: 260961194 | H210: 0
A211: L0000210 | B211: J00000021 | C211: BR005 | D211: 2000 | E211: 0050000012 | F211: MMK | G211: 0 | H211: 1109796
A212: L0000211 | B212: J00000021 | C212: BR005 | D212: 2000 | E212: 0050000019 | F212: MMK | G212: 0 | H212: 105764
A213: L0000212 | B213: J00000021 | C213: BR005 | D213: 2010 | E213: 0050000020 | F213: MMK | G213: 0 | H213: 606153
A214: L0000213 | B214: J00000021 | C214: BR005 | D214: 2000 | E214: 0050000039 | F214: MMK | G214: 0 | H214: 1231619
A215: L0000214 | B215: J00000021 | C215: BR005 | D215: 2000 | E215: 0050000040 | F215: MMK | G215: 0 | H215: 1542349
A216: L0000215 | B216: J00000021 | C216: BR005 | D216: 2000 | E216: 0050000042 | F216: MMK | G216: 0 | H216: 834364
A217: L0000216 | B217: J00000021 | C217: BR005 | D217: 2000 | E217: 0050000080 | F217: MMK | G217: 0 | H217: 6001467
A218: L0000217 | B218: J00000021 | C218: BR005 | D218: 2000 | E218: 0050000089 | F218: MMK | G218: 0 | H218: 453856
A219: L0000218 | B219: J00000021 | C219: BR005 | D219: 2010 | E219: 0050000099 | F219: MMK | G219: 0 | H219: 20580764
A220: L0000219 | B220: J00000021 | C220: BR005 | D220: 2000 | E220: 0050000117 | F220: MMK | G220: 0 | H220: 153426
A221: L0000220 | B221: J00000021 | C221: BR005 | D221: 2000 | E221: 0050000137 | F221: MMK | G221: 0 | H221: 194726
A222: L0000221 | B222: J00000021 | C222: BR005 | D222: 2010 | E222: 0050000138 | F222: MMK | G222: 0 | H222: 3112714
... A255: L0000254 | B255: J00000021 | C255: BR005 | D255: 2020 | E255: 0050000435 | F255: MMK | G255: 0 | H255: 9197046
A256: L0000255 | B256: J00000021 | C256: BR005 | D256: 1900 | F256: MMK | G256: 371855503 | H256: 0
A257: L0000256 | B257: J00000022 | C257: BR006 | D257: 2000 | E257: 0060000003 | F257: MMK | G257: 0 | H257: 268890
A258: L0000257 | B258: J00000022 | C258: BR006 | D258: 2010 | E258: 0060000004 | F258: MMK | G258: 0 | H258: 3458084
A259: L0000258 | B259: J00000022 | C259: BR006 | D259: 2000 | E259: 0060000006 | F259: MMK | G259: 0 | H259: 5000000
A260: L0000259 | B260: J00000022 | C260: BR006 | D260: 2010 | E260: 0060000007 | F260: MMK | G260: 0 | H260: 380935
A261: L0000260 | B261: J00000022 | C261: BR006 | D261: 2010 | E261: 0060000022 | F261: MMK | G261: 0 | H261: 52948000
A262: L0000261 | B262: J00000022 | C262: BR006 | D262: 2000 | E262: 0060000023 | F262: MMK | G262: 0 | H262: 5516280
A263: L0000262 | B263: J00000022 | C263: BR006 | D263: 2000 | E263: 0060000027 | F263: MMK | G263: 0 | H263: 2035472
A264: L0000263 | B264: J00000022 | C264: BR006 | D264: 2000 | E264: 0060000032 | F264: MMK | G264: 0 | H264: 934398
A265: L0000264 | B265: J00000022 | C265: BR006 | D265: 2000 | E265: 0060000058 | F265: MMK | G265: 0 | H265: 17463805
A266: L0000265 | B266: J00000022 | C266: BR006 | D266: 2010 | E266: 0060000059 | F266: MMK | G266: 0 | H266: 836932
A267: L0000266 | B267: J00000022 | C267: BR006 | D267: 2000 | E267: 0060000095 | F267: MMK | G267: 0 | H267: 897270
A268: L0000267 | B268: J00000022 | C268: BR006 | D268: 2000 | E268: 0060000103 | F268: MMK | G268: 0 | H268: 6658101
... A302: L0000301 | B302: J00000022 | C302: BR006 | D302: 2020 | E302: 0060000439 | F302: MMK | G302: 0 | H302: 25586120
A303: L0000302 | B303: J00000022 | C303: BR006 | D303: 1900 | F303: MMK | G303: 303263158 | H303: 0
A304: L0000303 | B304: J00000023 | C304: BR007 | D304: 2000 | E304: 0070000014 | F304: MMK | G304: 0 | H304: 3426075
A305: L0000304 | B305: J00000023 | C305: BR007 | D305: 2010 | E305: 0070000026 | F305: MMK | G305: 0 | H305: 3939447
...

Sheet DailyClose
A1: BusinessDate | B1: RunAt | C1: AccountsAccrued | D1: InterestAccrued | E1: InterbankSettled | F1: FDMatured | G1: DormantMarked | H1: ChecksPassed | I1: Notes
A2: 46296 | B2: 46296.75 | C2: 436 | D2: 313164.74 | E2: 0 | F2: 0 | G2: 0 | H2: Yes | I2: Sample end of day
A3: 46297 | B3: 46297.75 | C3: 437 | D3: 314606.51 | E3: 1 | F3: 0 | G3: 0 | H3: Yes | I3: Sample end of day
A4: 46298 | B4: 46298.75 | C4: 438 | D4: 318656.45 | E4: 1 | F4: 0 | G4: 0 | H4: Yes | I4: Sample end of day
A5: 46299 | B5: 46299.75 | C5: 439 | D5: 319109.29 | E5: 2 | F5: 0 | G5: 0 | H5: Yes | I5: Sample end of day
A6: 46300 | B6: 46300.75 | C6: 440 | D6: 319918.51 | E6: 4 | F6: 0 | G6: 0 | H6: Yes | I6: Sample end of day
A7: 46301 | B7: 46301.75 | C7: 441 | D7: 320748.9 | E7: 2 | F7: 0 | G7: 0 | H7: Yes | I7: Sample end of day
A8: 46302 | B8: 46302.75 | C8: 442 | D8: 322720.97 | E8: 1 | F8: 0 | G8: 0 | H8: Yes | I8: Sample end of day
A9: 46303 | B9: 46303.75 | C9: 443 | D9: 323019.02 | E9: 3 | F9: 0 | G9: 0 | H9: Yes | I9: Sample end of day
A10: 46304 | B10: 46304.75 | C10: 444 | D10: 325635.81 | E10: 4 | F10: 0 | G10: 0 | H10: Yes | I10: Sample end of day
A11: 46305 | B11: 46305.75 | C11: 444 | D11: 326803.14 | E11: 2 | F11: 0 | G11: 0 | H11: Yes | I11: Sample end of day
A12: 46306 | B12: 46306.75 | C12: 444 | D12: 327846.59 | E12: 2 | F12: 0 | G12: 0 | H12: Yes | I12: Sample end of day
A13: 46307 | B13: 46307.75 | C13: 444 | D13: 328963.65 | E13: 1 | F13: 0 | G13: 0 | H13: Yes | I13: Sample end of day

Sheet Audit
A1: AuditID | B1: Timestamp | C1: UserID | D1: Action | E1: Target | F1: Detail

Sheet Log
A1: Timestamp | B1: Level | C1: Procedure | D1: Message

Sheet Currencies
A1: Code | B1: Name | C1: Decimals | D1: IsBase
A2: MMK | B2: Myanmar kyat | C2: 0 | D2: Yes
A3: USD | B3: US dollar | C3: 2 | D3: No
A4: JPY | B4: Japanese yen | C4: 0 | D4: No
A5: THB | B5: Thai baht | C5: 2 | D5: No
A6: SGD | B6: Singapore dollar | C6: 2 | D6: No

Sheet ExchangeRates
A1: RateDate | B1: Currency | C1: BuyRate | D1: SellRate | E1: MidRate
A2: 46279 | B2: USD | C2: 2135.55 | D2: 2178.69 | E2: 2157.12
A3: 46279 | B3: JPY | C3: 14.48 | D3: 14.78 | E3: 14.63
A4: 46279 | B4: THB | C4: 62.27 | D4: 63.53 | E4: 62.9
A5: 46279 | B5: SGD | C5: 1635.37 | D5: 1668.41 | E5: 1651.89
A6: 46280 | B6: USD | C6: 2128.56 | D6: 2171.57 | E6: 2150.07
A7: 46280 | B7: JPY | C7: 14.52 | D7: 14.82 | E7: 14.67
A8: 46280 | B8: THB | C8: 62.28 | D8: 63.54 | E8: 62.91
A9: 46280 | B9: SGD | C9: 1640.71 | D9: 1673.85 | E9: 1657.28
A10: 46281 | B10: USD | C10: 2126.11 | D10: 2169.06 | E10: 2147.58
A11: 46281 | B11: JPY | C11: 14.49 | D11: 14.78 | E11: 14.64
A12: 46281 | B12: THB | C12: 62.3 | D12: 63.56 | E12: 62.93
A13: 46281 | B13: SGD | C13: 1640.74 | D13: 1673.89 | E13: 1657.32
... A121: 46308 | B121: SGD | C121: 1659.39 | D121: 1692.92 | E121: 1676.16

Sheet TaxRates
A1: TaxCode | B1: Name | C1: Rate | D1: AppliesTo | E1: GLCode | F1: EffectiveFrom
A2: WHT_INTEREST | B2: Withholding tax on deposit interest | C2: 0.1 | D2: Interest paid to customers | E2: 2200 | F2: 46023
A3: COMMERCIAL_FEES | B3: Commercial tax on fee income | C3: 0.05 | D3: Fee income | E3: 2210 | F3: 46023
A4: INCOME_TAX | B4: Income tax on annual profit | C4: 0.25 | D4: Annual profit | E4: 2220 | F4: 46023
A5: PAYROLL_SSB | B5: Employer social security contribution | C5: 0.03 | D5: Salaries | E5: 2230 | F5: 46023

Sheet BranchCosts
A1: CostID | B1: BranchID | C1: CostType | D1: Description | E1: Frequency | F1: Amount | G1: GLCode | H1: StartDate | I1: EndDate | J1: Status
A2: BC0001 | B2: BR001 | C2: Electricity | D2: Electricity for Head Office | E2: Monthly | F2: 5683000 | G2: 5210 | H2: 39539 | J2: Active
A3: BC0002 | B3: BR001 | C3: Water | D3: Water for Head Office | E3: Monthly | F3: 358000 | G3: 5211 | H3: 39539 | J3: Active
A4: BC0003 | B4: BR001 | C4: Internet and phone | D4: Internet and phone for Head Office | E4: Monthly | F4: 3658000 | G4: 5212 | H4: 39539 | J4: Active
A5: BC0004 | B5: BR001 | C5: Security guard service | D5: Security guard service for Head Office | E5: Monthly | F5: 3923000 | G5: 5230 | H5: 39539 | J5: Active
A6: BC0005 | B6: BR001 | C6: Cleaning service | D6: Cleaning service for Head Office | E6: Monthly | F6: 1819000 | G6: 5230 | H6: 39539 | J6: Active
A7: BC0006 | B7: BR001 | C7: Maintenance contract | D7: Maintenance contract for Head Office | E7: Monthly | F7: 2879000 | G7: 5220 | H7: 39539 | J7: Active
A8: BC0007 | B8: BR001 | C8: Stationery and supplies | D8: Stationery and supplies for Head Office | E8: Monthly | F8: 1735000 | G8: 5270 | H8: 39539 | J8: Active
A9: BC0008 | B9: BR001 | C9: Generator fuel | D9: Generator fuel for Head Office | E9: Monthly | F9: 1503000 | G9: 5280 | H9: 39539 | J9: Active
A10: BC0009 | B10: BR001 | C10: Insurance | D10: Insurance for Head Office | E10: Yearly | F10: 31005000 | G10: 5240 | H10: 39539 | J10: Active
A11: BC0010 | B11: BR001 | C11: Property tax and licences | D11: Property tax and licences for Head Office | E11: Yearly | F11: 11761000 | G11: 5260 | H11: 39539 | J11: Active
A12: BC0011 | B12: BR002 | C12: Electricity | D12: Electricity for Hlaing Branch | E12: Monthly | F12: 1842000 | G12: 5210 | H12: 40330 | J12: Active
A13: BC0012 | B13: BR002 | C13: Water | D13: Water for Hlaing Branch | E13: Monthly | F13: 147000 | G13: 5211 | H13: 40330 | J13: Active
... A151: BC0150 | B151: BR015 | C151: Rent | D151: Rent for Nyaung-U Branch | E151: Monthly | F151: 1903000 | G151: 5200 | H151: 43831 | J151: Active

Sheet FixedAssets
A1: AssetID | B1: BranchID | C1: AssetType | D1: Description | E1: AcquireDate | F1: Cost | G1: UsefulLifeMonths | H1: ResidualValue | I1: DepMethod | J1: AccumDepAt20260930 | K1: Status
A2: FA0001 | B2: BR001 | C2: Building | D2: Building, Head Office | E2: 43958 | F2: 8000000000 | G2: 480 | H2: 0 | I2: StraightLine | J2: 1266666666 | K2: InUse
A3: FA0002 | B3: BR001 | C3: Vault and safe | D3: Vault and safe, Head Office | E3: 45644 | F3: 45000000 | G3: 240 | H3: 2250000 | I3: StraightLine | J3: 3740625 | K3: InUse
A4: FA0003 | B4: BR001 | C4: Generator | D4: Generator, Head Office | E4: 45614 | F4: 35000000 | G4: 120 | H4: 1750000 | I4: StraightLine | J4: 6095833 | K4: InUse
A5: FA0004 | B5: BR001 | C5: Computers and network | D5: Computers and network, Head Office | E5: 45407 | F5: 28000000 | G5: 48 | H5: 1400000 | I5: StraightLine | J5: 16070833 | K5: InUse
A6: FA0005 | B6: BR001 | C6: Furniture | D6: Furniture, Head Office | E6: 45538 | F6: 15000000 | G6: 96 | H6: 750000 | I6: StraightLine | J6: 3562500 | K6: InUse
A7: FA0006 | B7: BR001 | C7: Air conditioning | D7: Air conditioning, Head Office | E7: 44427 | F7: 12000000 | G7: 96 | H7: 600000 | I7: StraightLine | J7: 7243750 | K7: InUse
A8: FA0007 | B8: BR001 | C8: Vehicle | D8: Vehicle, Head Office | E8: 43814 | F8: 90000000 | G8: 96 | H8: 4500000 | I8: StraightLine | J8: 72140625 | K8: InUse
A9: FA0008 | B9: BR002 | C9: Vault and safe | D9: Vault and safe, Hlaing Branch | E9: 44715 | F9: 45000000 | G9: 240 | H9: 2250000 | I9: StraightLine | J9: 9084375 | K9: InUse
A10: FA0009 | B10: BR002 | C10: Generator | D10: Generator, Hlaing Branch | E10: 43946 | F10: 35000000 | G10: 120 | H10: 1750000 | I10: StraightLine | J10: 21335416 | K10: InUse
A11: FA0010 | B11: BR002 | C11: Computers and network | D11: Computers and network, Hlaing Branch | E11: 44552 | F11: 28000000 | G11: 48 | H11: 1400000 | I11: StraightLine | J11: 26600000 | K11: InUse
A12: FA0011 | B12: BR002 | C12: Furniture | D12: Furniture, Hlaing Branch | E12: 44801 | F12: 15000000 | G12: 96 | H12: 750000 | I12: StraightLine | J12: 7273437 | K12: InUse
A13: FA0012 | B13: BR002 | C13: Air conditioning | D13: Air conditioning, Hlaing Branch | E13: 44140 | F13: 12000000 | G13: 96 | H13: 600000 | I13: StraightLine | J13: 8312500 | K13: InUse
... A90: FA0089 | B90: BR015 | C90: Air conditioning | D90: Air conditioning, Nyaung-U Branch | E90: 45777 | F90: 5000000 | G90: 96 | H90: 250000 | I90: StraightLine | J90: 841145 | K90: InUse
